[{"faction":"Tuatha Dé Danann","classes":[{"class":"Blessed Crow","trees":[{"name":"Class Abilities","abilities":{"Armor of Faith":{"type":"Spell","cast_speed":"0.2s","base_value":null,"resource_delta":"None","range":"Self","summary":"Increases your Physical Armor by 70% for 8 seconds. 60.0s Cooldown.","generative_icon":"\u003csvg class=\"w-6 h-6\" fill=\"none\" stroke=\"currentColor\" viewBox=\"0 0 24 24\" aria-hidden=\"true\" stroke-width=\"1.75\" stroke-linecap=\"round\" stroke-linejoin=\"round\"\u003e\u003cpath d=\"M12 3l7 3v6c0 4.5-3 7.5-7 9-4-1.5-7-4.5-7-9V6l7-3z\"/\u003e\u003cpath d=\"M12 8v4M10 10h4\"/\u003e\u003c/svg\u003e"},"Rally":{"type":"Spell","cast_speed":"0.2s","base_value":"Strong Heal Over Time","resource_delta":"-2 Judgment, +500 Faith","range":"90m","summary":"Grants your party a strong Heal Over Time for 6 seconds. 6.0s Cooldown.","generative_icon":"\u003csvg class=\"w-6 h-6\" fill=\"none\" stroke=\"currentColor\" viewBox=\"0 0 24 24\" aria-hidden=\"true\" stroke-width=\"1.75\" stroke-linecap=\"round\" stroke-linejoin=\"round\"\u003e\u003cpath d=\"M5 4v16\"/\u003e\u003cpath d=\"M5 4h9l-3 4 3 4H5\"/\u003e\u003cpath d=\"M16 9c2 .5 3 2 3 3.5S18 16 16 17\"/\u003e\u003c/svg\u003e"}}},{"name":"Dominance","abilities":{"Crushing Might":{"type":"Damage","cast_speed":"0.6s","base_value":"972 Base Damage","resource_delta":"+1 Judgment","range":"6m","summary":"Deals Weapon damage.","generative_icon":"\u003csvg class=\"w-6 h-6\" fill=\"none\" stroke=\"currentColor\" viewBox=\"0 0 24 24\" aria-hidden=\"true\" stroke-width=\"1.75\" stroke-linecap=\"round\" stroke-linejoin=\"round\"\u003e\u003cpath d=\"M14 4l4 4-9 9H5v-4l9-9z\"/\u003e\u003cpath d=\"M16 6l2 2\"/\u003e\u003c/svg\u003e"},"Overwhelm":{"type":"Damage / Debuff","cast_speed":"0.6s","base_value":"4730 Damage","resource_delta":"-1 Judgment, +250 Faith","range":"6m","summary":"Deals Shadow damage; target takes +50% damage from this ability for 6s.","generative_icon":"\u003csvg class=\"w-6 h-6\" fill=\"none\" stroke=\"currentColor\" viewBox=\"0 0 24 24\" aria-hidden=\"true\" stroke-width=\"1.75\" stroke-linecap=\"round\" stroke-linejoin=\"round\"\u003e\u003cpath d=\"M12 3v12\"/\u003e\u003cpath d=\"M8 7l4-4 4 4\"/\u003e\u003cpath d=\"M6 19h12\"/\u003e\u003cpath d=\"M9 15h6\"/\u003e\u003c/svg\u003e"},"Strike of the Blessed":{"type":"Damage / Heal Over Time","cast_speed":"0.6s","base_value":"1944 Damage","resource_delta":"-1 Judgment, +250 Faith","range":"6m","summary":"Deals Spirit damage and heals self over time.","generative_icon":"\u003csvg class=\"w-6 h-6\" fill=\"none\" stroke=\"currentColor\" viewBox=\"0 0 24 24\" aria-hidden=\"true\" stroke-width=\"1.75\" stroke-linecap=\"round\" stroke-linejoin=\"round\"\u003e\u003cpath d=\"M14 3l3 3-8 8H5v-4l9-9z\"/\u003e\u003cpath d=\"M16 5l3 3\"/\u003e\u003ccircle cx=\"18\" cy=\"6\" r=\"1.5\"/\u003e\u003c/svg\u003e"},"Blessed Warrior":{"type":"Buff","cast_speed":"0.2s","base_value":null,"resource_delta":"None","range":"Self","summary":"Increases Melee damage dealt and Parry Chance. (Spell)","generative_icon":"\u003csvg class=\"w-6 h-6\" fill=\"none\" stroke=\"currentColor\" viewBox=\"0 0 24 24\" aria-hidden=\"true\" stroke-width=\"1.75\" stroke-linecap=\"round\" stroke-linejoin=\"round\"\u003e\u003cpath d=\"M8 20l4-14 4 14\"/\u003e\u003cpath d=\"M6 12h12\"/\u003e\u003ccircle cx=\"12\" cy=\"4\" r=\"2\"/\u003e\u003c/svg\u003e"},"Living Symbol":{"type":"Buff / Aura","cast_speed":"0.2s","base_value":null,"resource_delta":"-2 Judgment, +500 Faith","range":"Self (Aura)","summary":"Creates an aura granting Physical/Magical armor and Panic Resistance to nearby allies. 15.0s Cooldown. (Spell)","generative_icon":"\u003csvg class=\"w-6 h-6\" fill=\"none\" stroke=\"currentColor\" viewBox=\"0 0 24 24\" aria-hidden=\"true\" stroke-width=\"1.75\" stroke-linecap=\"round\" stroke-linejoin=\"round\"\u003e\u003ccircle cx=\"12\" cy=\"12\" r=\"3\"/\u003e\u003cpath d=\"M12 3v2M12 19v2M3 12h2M19 12h2M5.6 5.6l1.4 1.4M17 17l1.4 1.4M5.6 18.4l1.4-1.4M17 7l1.4-1.4\"/\u003e\u003c/svg\u003e"},"Sacred Pride":{"type":"Damage / CC","cast_speed":"0.6s","base_value":"1080 Damage","resource_delta":"-125 Faith, +3 Judgment","range":"6m","summary":"Deals Weapon damage and Snares the target by 40% for 4/8s. 30.0s Cooldown.","generative_icon":"\u003csvg class=\"w-6 h-6\" fill=\"none\" stroke=\"currentColor\" viewBox=\"0 0 24 24\" aria-hidden=\"true\" stroke-width=\"1.75\" stroke-linecap=\"round\" stroke-linejoin=\"round\"\u003e\u003cpath d=\"M13 2L5 14h6l-1 8 9-14h-6l1-6z\"/\u003e\u003ccircle cx=\"17\" cy=\"19\" r=\"2\"/\u003e\u003c/svg\u003e"},"Scorn the Weak":{"type":"CC / Debuff","cast_speed":"0.2s","base_value":null,"resource_delta":"-150 Faith, +Judgment","range":"25m","summary":"Snares the target and reduces damage dealt by 30%. 30.0s Cooldown. (Spell)","generative_icon":"\u003csvg class=\"w-6 h-6\" fill=\"none\" stroke=\"currentColor\" viewBox=\"0 0 24 24\" aria-hidden=\"true\" stroke-width=\"1.75\" stroke-linecap=\"round\" stroke-linejoin=\"round\"\u003e\u003cpath d=\"M9 4l1 8\"/\u003e\u003cpath d=\"M10 12c3 0 5 2 5 5\"/\u003e\u003cpath d=\"M6 20l3-3\"/\u003e\u003cpath d=\"M15 20l-3-3\"/\u003e\u003c/svg\u003e"},"Avatar of Bran":{"type":"Buff","cast_speed":"0.2s","base_value":null,"resource_delta":"None","range":"Self","summary":"Grants 70 Physical/Magic Armor and increases Weaponskill damage for 10s. Next Melee hit gains strong Spirit damage. 120.0s Cooldown. (Spell, Ritual)","generative_icon":"\u003csvg class=\"w-6 h-6\" fill=\"none\" stroke=\"currentColor\" viewBox=\"0 0 24 24\" aria-hidden=\"true\" stroke-width=\"1.75\" stroke-linecap=\"round\" stroke-linejoin=\"round\"\u003e\u003cpath d=\"M12 4c-2 2-4 4-4 7 0 3 1.8 5 4 6 2.2-1 4-3 4-6 0-3-2-5-4-7z\"/\u003e\u003cpath d=\"M8 6l-2-2M16 6l2-2\"/\u003e\u003cpath d=\"M12 17v3\"/\u003e\u003c/svg\u003e"}}},{"name":"Ritual","abilities":{"Summon Cauldron":{"type":"Spell (Ground)","cast_speed":"0.2s","base_value":"Max 4 Cauldrons total","resource_delta":"None","range":"25m","summary":"Summons a Cauldron at the targeted location for 60 seconds. Maximum of 4 Cauldrons total from all abilities. 6.0s Cooldown.","generative_icon":"\u003csvg class=\"w-6 h-6\" fill=\"none\" stroke=\"currentColor\" viewBox=\"0 0 24 24\" aria-hidden=\"true\" stroke-width=\"1.75\" stroke-linecap=\"round\" stroke-linejoin=\"round\"\u003e\u003cpath d=\"M6 10c0-2 2.7-4 6-4s6 2 6 4\"/\u003e\u003cpath d=\"M5 10h14v2c0 3-3 5-7 5s-7-2-7-5v-2z\"/\u003e\u003cpath d=\"M8 19h8\"/\u003e\u003c/svg\u003e"},"Nature\u0027s Rebuke":{"type":"Damage / CC","cast_speed":"0.6s","base_value":"864 Base Damage","resource_delta":"+1 Judgment","range":"6m","summary":"Deals Weapon damage and Snares the target by 40% for 4/8 seconds.","generative_icon":"\u003csvg class=\"w-6 h-6\" fill=\"none\" stroke=\"currentColor\" viewBox=\"0 0 24 24\" aria-hidden=\"true\" stroke-width=\"1.75\" stroke-linecap=\"round\" stroke-linejoin=\"round\"\u003e\u003cpath d=\"M6 20c4-6 8-10 12-12\"/\u003e\u003cpath d=\"M14 6l4-2\"/\u003e\u003cpath d=\"M10 10l-3-2\"/\u003e\u003cpath d=\"M16 14l2 3\"/\u003e\u003c/svg\u003e"},"Dark Work":{"type":"Spell (AoE)","cast_speed":"1.0s","base_value":"720 Base Damage","resource_delta":"-150 Faith, +1 Judgment","range":"45m (8m AoE Radius)","summary":"Deals Shadow damage to enemies near each of your Cauldrons.","generative_icon":"\u003csvg class=\"w-6 h-6\" fill=\"none\" stroke=\"currentColor\" viewBox=\"0 0 24 24\" aria-hidden=\"true\" stroke-width=\"1.75\" stroke-linecap=\"round\" stroke-linejoin=\"round\"\u003e\u003cpath d=\"M7 11c0-2 2.2-3 5-3s5 1 5 3\"/\u003e\u003cpath d=\"M6 11h10v2c0 2.5-2 4-5 4s-5-1.5-5-4v-2z\"/\u003e\u003cpath d=\"M9 7c1-2 3-3 5-3\"/\u003e\u003cpath d=\"M14 4c1 1 2 2 2 4\"/\u003e\u003c/svg\u003e"},"Blood Offering":{"type":"Damage / Summon","cast_speed":"0.6s","base_value":"1836 Base Damage","resource_delta":"None","range":"6m","summary":"Deals Weapon damage and summons a Cauldron at the target\u0027s location for 60 seconds. 10.0s Cooldown.","generative_icon":"\u003csvg class=\"w-6 h-6\" fill=\"none\" stroke=\"currentColor\" viewBox=\"0 0 24 24\" aria-hidden=\"true\" stroke-width=\"1.75\" stroke-linecap=\"round\" stroke-linejoin=\"round\"\u003e\u003cpath d=\"M12 4c-2 3-4 5-4 7a4 4 0 108 0c0-2-2-4-4-7z\"/\u003e\u003cpath d=\"M6 17c0-2 2.2-3 5-3s5 1 5 3\"/\u003e\u003cpath d=\"M5 17h10v2c0 2-2 3.5-5 3.5S5 21 5 19v-2z\"/\u003e\u003c/svg\u003e"},"Rite of Healing":{"type":"Spell (AoE)","cast_speed":"0.2s","base_value":"Periodic Heal","resource_delta":"-2 Judgment, +500 Faith","range":"45m (15m AoE Radius)","summary":"Periodically heals allies near each of your Cauldrons. 6.0s Cooldown.","generative_icon":"\u003csvg class=\"w-6 h-6\" fill=\"none\" stroke=\"currentColor\" viewBox=\"0 0 24 24\" aria-hidden=\"true\" stroke-width=\"1.75\" stroke-linecap=\"round\" stroke-linejoin=\"round\"\u003e\u003cpath d=\"M6 14c0-2 2.2-3 5-3s5 1 5 3\"/\u003e\u003cpath d=\"M5 14h10v2c0 2-2 3-5 3s-5-1-5-3v-2z\"/\u003e\u003cpath d=\"M8 9c1-1 2-2 4-2\"/\u003e\u003cpath d=\"M10 5c0 1 .5 2 1.5 2.5\"/\u003e\u003c/svg\u003e"},"Call Down":{"type":"Spell (Ground AoE)","cast_speed":"1.0s","base_value":"1170 Base Damage","resource_delta":"None","range":"25m (8m AoE Radius)","summary":"Summons a Cauldron for 60s and deals Spirit damage in the targeted area. 12.0s Cooldown.","generative_icon":"\u003csvg class=\"w-6 h-6\" fill=\"none\" stroke=\"currentColor\" viewBox=\"0 0 24 24\" aria-hidden=\"true\" stroke-width=\"1.75\" stroke-linecap=\"round\" stroke-linejoin=\"round\"\u003e\u003cpath d=\"M12 4v8\"/\u003e\u003cpath d=\"M9 9l3 3 3-3\"/\u003e\u003ccircle cx=\"12\" cy=\"18\" r=\"3\"/\u003e\u003cpath d=\"M10 18h4\"/\u003e\u003c/svg\u003e"},"Rite of Sickness":{"type":"Spell (AoE)","cast_speed":"0.2s","base_value":"720 Base Damage","resource_delta":"-1 Judgment, +250 Faith","range":"45m (8m AoE Radius)","summary":"Deals Spirit damage to and Snares enemies near each of your Cauldrons. 4.0s Cooldown.","generative_icon":"\u003csvg class=\"w-6 h-6\" fill=\"none\" stroke=\"currentColor\" viewBox=\"0 0 24 24\" aria-hidden=\"true\" stroke-width=\"1.75\" stroke-linecap=\"round\" stroke-linejoin=\"round\"\u003e\u003cpath d=\"M7 12c0-2 2.2-3 5-3s5 1 5 3\"/\u003e\u003cpath d=\"M6 12h10v2c0 2-2 3-5 3s-5-1-5-3v-2z\"/\u003e\u003cpath d=\"M9 8l6 6M15 8l-6 6\"/\u003e\u003c/svg\u003e"},"Conduit of Power":{"type":"Damage","cast_speed":"0.6s","base_value":"1339 Base Damage","resource_delta":"-1 Judgment, +250 Faith","range":"6m","summary":"Deals Spirit damage. Damage is increased by 50% for each nearby Cauldron.","generative_icon":"\u003csvg class=\"w-6 h-6\" fill=\"none\" stroke=\"currentColor\" viewBox=\"0 0 24 24\" aria-hidden=\"true\" stroke-width=\"1.75\" stroke-linecap=\"round\" stroke-linejoin=\"round\"\u003e\u003cpath d=\"M5 16c0-1 1-2 2.5-2S10 15 10 16\"/\u003e\u003cpath d=\"M4 16h3v2c0 1 1 1.5 2.5 1.5\"/\u003e\u003cpath d=\"M14 16c0-1 1-2 2.5-2s2.5 1 2.5 2\"/\u003e\u003cpath d=\"M13 16h3v2c0 1 1 1.5 2.5 1.5\"/\u003e\u003cpath d=\"M10 12h4M12 10v4\"/\u003e\u003c/svg\u003e"},"Rite of Ruin":{"type":"Spell (AoE)","cast_speed":"0.2s","base_value":"Damage Taken Debuff","resource_delta":"-3 Judgment, +750 Faith","range":"45m","summary":"Creates auras around you and your Cauldrons that cause enemies to take increased damage. This effect stacks. 4.0s Cooldown.","generative_icon":"\u003csvg class=\"w-6 h-6\" fill=\"none\" stroke=\"currentColor\" viewBox=\"0 0 24 24\" aria-hidden=\"true\" stroke-width=\"1.75\" stroke-linecap=\"round\" stroke-linejoin=\"round\"\u003e\u003cpath d=\"M7 13c0-2 2.2-3 5-3s5 1 5 3\"/\u003e\u003cpath d=\"M6 13h10v2c0 2-2 3-5 3s-5-1-5-3v-2z\"/\u003e\u003cpath d=\"M8 8l8 8\"/\u003e\u003c/svg\u003e"}}},{"name":"Nourishment","abilities":{"Nurture Life":{"type":"Spell","cast_speed":"0.2s","base_value":null,"resource_delta":"-100 Faith, +1 Judgment","range":"25m","summary":"Heals the target over time. 2.0s Cooldown.","generative_icon":"\u003csvg class=\"w-6 h-6\" fill=\"none\" stroke=\"currentColor\" viewBox=\"0 0 24 24\" aria-hidden=\"true\" stroke-width=\"1.75\" stroke-linecap=\"round\" stroke-linejoin=\"round\"\u003e\u003cpath d=\"M12 20V10\"/\u003e\u003cpath d=\"M12 10c-3-2-5-4-5-6a5 5 0 0110 0c0 2-2 4-5 6z\"/\u003e\u003cpath d=\"M8 20h8\"/\u003e\u003c/svg\u003e"},"Branwen\u0027s Tears":{"type":"Healing","cast_speed":"1.0s","base_value":"2813 Healing","resource_delta":"-1 Judgment, +250 Faith","range":"45m","summary":"Heals target. (Spell)","generative_icon":"\u003csvg class=\"w-6 h-6\" fill=\"none\" stroke=\"currentColor\" viewBox=\"0 0 24 24\" aria-hidden=\"true\" stroke-width=\"1.75\" stroke-linecap=\"round\" stroke-linejoin=\"round\"\u003e\u003cpath d=\"M12 4c-1.5 2.5-4 5-4 8a4 4 0 008 0c0-3-2.5-5.5-4-8z\"/\u003e\u003cpath d=\"M10 18c.5 1 1.5 2 2 2s1.5-1 2-2\"/\u003e\u003c/svg\u003e"},"Cleansing Winds":{"type":"AoE Cleanse","cast_speed":"0.2s","base_value":"Removes 1 Debuff","resource_delta":"-150 Faith, +1 Judgment","range":"45m","summary":"Removes 1 Debuff from allies near you and near each Cauldron (can apply multiple times). 6.0s Cooldown. (Spell)","generative_icon":"\u003csvg class=\"w-6 h-6\" fill=\"none\" stroke=\"currentColor\" viewBox=\"0 0 24 24\" aria-hidden=\"true\" stroke-width=\"1.75\" stroke-linecap=\"round\" stroke-linejoin=\"round\"\u003e\u003cpath d=\"M4 10c2 0 3-1 5-1s3 1 5 1\"/\u003e\u003cpath d=\"M3 14c2.5 0 4-1 6.5-1s4 1 6.5 1\"/\u003e\u003cpath d=\"M15 8l3-2\"/\u003e\u003cpath d=\"M9 16l-2 2\"/\u003e\u003c/svg\u003e"},"Rise from the Cauldron":{"type":"Spell","cast_speed":"9.0s","base_value":null,"resource_delta":"-200 Faith","range":"25m (Friend)","summary":"Resurrects target ally with 15% max Health and Res Sickness.","generative_icon":"\u003csvg class=\"w-6 h-6\" fill=\"none\" stroke=\"currentColor\" viewBox=\"0 0 24 24\" aria-hidden=\"true\" stroke-width=\"1.75\" stroke-linecap=\"round\" stroke-linejoin=\"round\"\u003e\u003cpath d=\"M6 15c0-2 2.2-3 5-3s5 1 5 3\"/\u003e\u003cpath d=\"M5 15h10v2c0 2-2 3-5 3s-5-1-5-3v-2z\"/\u003e\u003cpath d=\"M12 6v5\"/\u003e\u003cpath d=\"M10 8l2-2 2 2\"/\u003e\u003c/svg\u003e"},"Regrowth":{"type":"Spell","cast_speed":"0.2s","base_value":"2250 Base Healing","resource_delta":"-2 Judgment, +500 Faith","range":"15m (AoE Radius)","summary":"Heals nearby allies. 2.0s Cooldown.","generative_icon":"\u003csvg class=\"w-6 h-6\" fill=\"none\" stroke=\"currentColor\" viewBox=\"0 0 24 24\" aria-hidden=\"true\" stroke-width=\"1.75\" stroke-linecap=\"round\" stroke-linejoin=\"round\"\u003e\u003ccircle cx=\"12\" cy=\"12\" r=\"2\"/\u003e\u003cpath d=\"M12 10V6M12 14v4M10 12H6M14 12h4M8.5 8.5L6 6M15.5 15.5L18 18M15.5 8.5L18 6M8.5 15.5L6 18\"/\u003e\u003c/svg\u003e"},"Dedicated Pursuit":{"type":"Spell","cast_speed":"0.2s","base_value":null,"resource_delta":"-125 Faith, +1 Judgment","range":"Self","summary":"Increases Movement Speed for 6 seconds. Becomes Dedicated Pursuit Follow-Up when used. 20.0s Cooldown.","generative_icon":"\u003csvg class=\"w-6 h-6\" fill=\"none\" stroke=\"currentColor\" viewBox=\"0 0 24 24\" aria-hidden=\"true\" stroke-width=\"1.75\" stroke-linecap=\"round\" stroke-linejoin=\"round\"\u003e\u003cpath d=\"M6 18c2-4 4-6 6-6s4 2 6 6\"/\u003e\u003cpath d=\"M8 18h8\"/\u003e\u003cpath d=\"M16 10l3-2M18 8l2 2\"/\u003e\u003c/svg\u003e"},"Bran\u0027s Aid":{"type":"Spell","cast_speed":"1.0s","base_value":"1500 Base Healing","resource_delta":"None","range":"45m (15m AoE Radius)","summary":"Heals allies in an area around target ally and summons a Cauldron at the target\u0027s location for 60 seconds. 12.0s Cooldown.","generative_icon":"\u003csvg class=\"w-6 h-6\" fill=\"none\" stroke=\"currentColor\" viewBox=\"0 0 24 24\" aria-hidden=\"true\" stroke-width=\"1.75\" stroke-linecap=\"round\" stroke-linejoin=\"round\"\u003e\u003cpath d=\"M8 11c0-1.5 1.5-2.5 4-2.5s4 1 4 2.5\"/\u003e\u003cpath d=\"M7 11h10v2c0 1.5-1.5 2.5-4 2.5S7 14.5 7 13v-2z\"/\u003e\u003cpath d=\"M12 5v3\"/\u003e\u003cpath d=\"M9 7h6\"/\u003e\u003c/svg\u003e"},"Bran\u0027s Gift":{"type":"Spell","cast_speed":"2.0s","base_value":null,"resource_delta":"None","range":"45m (8m AoE Radius)","summary":"Resurrects allies near each of your Cauldrons with 25% Max Health and Res Sickness. 180.0s Cooldown.","generative_icon":"\u003csvg class=\"w-6 h-6\" fill=\"none\" stroke=\"currentColor\" viewBox=\"0 0 24 24\" aria-hidden=\"true\" stroke-width=\"1.75\" stroke-linecap=\"round\" stroke-linejoin=\"round\"\u003e\u003cpath d=\"M7 14c0-2 2.2-3 5-3s5 1 5 3\"/\u003e\u003cpath d=\"M6 14h10v2c0 2-2 3-5 3s-5-1-5-3v-2z\"/\u003e\u003ccircle cx=\"10\" cy=\"6\" r=\"1\"/\u003e\u003ccircle cx=\"14\" cy=\"4\" r=\"1\"/\u003e\u003ccircle cx=\"12\" cy=\"8\" r=\"1\"/\u003e\u003c/svg\u003e"}}}]},{"class":"Dark Fool","trees":[{"name":"Class Abilities","abilities":{"Raise Morale":{"type":"Buff","cast_speed":"0.2s","base_value":null,"resource_delta":"None","range":"Party","summary":"Increases party morale and regeneration.","generative_icon":"\u003csvg class=\"w-6 h-6\" fill=\"none\" stroke=\"currentColor\" viewBox=\"0 0 24 24\" aria-hidden=\"true\" stroke-width=\"1.75\" stroke-linecap=\"round\" stroke-linejoin=\"round\"\u003e\u003cpath d=\"M12 16V7M9 10l3-3 3 3\"/\u003e\u003cpath d=\"M8 19c2-2 4-3 6-3s4 1 6 3\"/\u003e\u003c/svg\u003e"},"Song of Travel":{"type":"Buff","cast_speed":"0.2s","base_value":null,"resource_delta":"None","range":"Party","summary":"Increases party movement speed.","generative_icon":"\u003csvg class=\"w-6 h-6\" fill=\"none\" stroke=\"currentColor\" viewBox=\"0 0 24 24\" aria-hidden=\"true\" stroke-width=\"1.75\" stroke-linecap=\"round\" stroke-linejoin=\"round\"\u003e\u003cpath d=\"M6 18c2-3 4-5 6-5s4 2 6 5\"/\u003e\u003cpath d=\"M9 13l-1-2M15 13l1-2\"/\u003e\u003cpath d=\"M12 8v2\"/\u003e\u003c/svg\u003e"}}},{"name":"Night Terrors","abilities":{"A Sharpened Tongue":{"type":"Damage","cast_speed":"0.6s","base_value":"917 Damage (+50% vs Panicked)","resource_delta":"None","range":"70m","summary":"Deals Weapon damage; hits significantly harder against Panicked targets.","generative_icon":"\u003csvg class=\"w-6 h-6\" fill=\"none\" stroke=\"currentColor\" viewBox=\"0 0 24 24\" aria-hidden=\"true\" stroke-width=\"1.75\" stroke-linecap=\"round\" stroke-linejoin=\"round\"\u003e\u003cpath d=\"M8 8c2 0 3 1 4 3\"/\u003e\u003cpath d=\"M12 11l4 5\"/\u003e\u003cpath d=\"M6 18l2-4\"/\u003e\u003c/svg\u003e"},"Cutting Whispers":{"type":"Damage","cast_speed":"0.6s","base_value":"1376 Mind Damage","resource_delta":"-150 Focus","range":"70m","summary":"Deals Mind damage.","generative_icon":"\u003csvg class=\"w-6 h-6\" fill=\"none\" stroke=\"currentColor\" viewBox=\"0 0 24 24\" aria-hidden=\"true\" stroke-width=\"1.75\" stroke-linecap=\"round\" stroke-linejoin=\"round\"\u003e\u003cpath d=\"M4 8c3 0 5 2 7 2s4-2 7-2\"/\u003e\u003cpath d=\"M3 12c3 1 5 3 8 3s5-2 8-3\"/\u003e\u003cpath d=\"M16 6l3-2\"/\u003e\u003c/svg\u003e"},"In Darkest Dreams":{"type":"AoE Damage","cast_speed":"2.0s","base_value":"Mind Damage per second","resource_delta":"-225 Focus","range":"60m (10m AoE, Ground)","summary":"Creates a cloud for 12s dealing Mind damage per second. 15.0s Cooldown. (Spell)","generative_icon":"\u003csvg class=\"w-6 h-6\" fill=\"none\" stroke=\"currentColor\" viewBox=\"0 0 24 24\" aria-hidden=\"true\" stroke-width=\"1.75\" stroke-linecap=\"round\" stroke-linejoin=\"round\"\u003e\u003cpath d=\"M21 14a9 9 0 11-18 0\"/\u003e\u003cpath d=\"M9 10h.01M15 10h.01\"/\u003e\u003cpath d=\"M8 15c1 1 2.5 1.5 4 1.5s3-.5 4-1.5\"/\u003e\u003c/svg\u003e"},"With Claws That Tear":{"type":"Group Buff","cast_speed":"3.0s","base_value":"+50 Panic on Hit","resource_delta":"None","range":"90m Aura","summary":"Party\u0027s Direct Damage also inflicts 50 Panic. (Spell)","generative_icon":"\u003csvg class=\"w-6 h-6\" fill=\"none\" stroke=\"currentColor\" viewBox=\"0 0 24 24\" aria-hidden=\"true\" stroke-width=\"1.75\" stroke-linecap=\"round\" stroke-linejoin=\"round\"\u003e\u003cpath d=\"M8 6l-1 4M11 5l-1 5M14 6l-1 4\"/\u003e\u003cpath d=\"M7 14c2 3 4 4 6 4\"/\u003e\u003c/svg\u003e"},"Look Upon Oblivion":{"type":"Damage Over Time","cast_speed":"0.2s","base_value":"3000 Mind Damage over 12s","resource_delta":"None","range":"60m","summary":"Deals high-value pressure damage over time. 60.0s Cooldown. (Spell)","generative_icon":"\u003csvg class=\"w-6 h-6\" fill=\"none\" stroke=\"currentColor\" viewBox=\"0 0 24 24\" aria-hidden=\"true\" stroke-width=\"1.75\" stroke-linecap=\"round\" stroke-linejoin=\"round\"\u003e\u003ccircle cx=\"12\" cy=\"12\" r=\"8\"/\u003e\u003ccircle cx=\"12\" cy=\"12\" r=\"2\"/\u003e\u003cpath d=\"M12 4v2M12 18v2\"/\u003e\u003c/svg\u003e"},"A Grand Tragedy":{"type":"Group Buff","cast_speed":"3.0s","base_value":"+20% Damage vs Controlled","resource_delta":"None","range":"90m Aura","summary":"Party deals 20% increased damage vs targets under Control effects. (Spell)","generative_icon":"\u003csvg class=\"w-6 h-6\" fill=\"none\" stroke=\"currentColor\" viewBox=\"0 0 24 24\" aria-hidden=\"true\" stroke-width=\"1.75\" stroke-linecap=\"round\" stroke-linejoin=\"round\"\u003e\u003cpath d=\"M8 10c0-2 1.5-3 4-3s4 1 4 3\"/\u003e\u003cpath d=\"M6 16c2-2 4-3 6-3s4 1 6 3\"/\u003e\u003cpath d=\"M16 8l2-2\"/\u003e\u003c/svg\u003e"},"That Stalk the Night":{"type":"Group Buff / Mitigation","cast_speed":"0.2s","base_value":"-40% Non-Melee Damage Taken","resource_delta":"None","range":"90m Aura","summary":"Increases party Movement Speed and decreases non-Melee damage taken by 40% for 6s. 60.0s Cooldown. (Spell)","generative_icon":"\u003csvg class=\"w-6 h-6\" fill=\"none\" stroke=\"currentColor\" viewBox=\"0 0 24 24\" aria-hidden=\"true\" stroke-width=\"1.75\" stroke-linecap=\"round\" stroke-linejoin=\"round\"\u003e\u003cpath d=\"M6 16c2-4 4-6 6-6\"/\u003e\u003cpath d=\"M14 10l4-2\"/\u003e\u003ccircle cx=\"17\" cy=\"8\" r=\"1\"/\u003e\u003cpath d=\"M8 18h8\"/\u003e\u003c/svg\u003e"},"The Cruelest Joke":{"type":"AoE CC / Damage","cast_speed":"2.0s","base_value":"1000 Shadow Damage over 5s","resource_delta":"-350 Focus","range":"60m (8m AoE)","summary":"Snares by 40% and inflicts DoT. If target dies, nearby allies are Feared. (Spell)","generative_icon":"\u003csvg class=\"w-6 h-6\" fill=\"none\" stroke=\"currentColor\" viewBox=\"0 0 24 24\" aria-hidden=\"true\" stroke-width=\"1.75\" stroke-linecap=\"round\" stroke-linejoin=\"round\"\u003e\u003cpath d=\"M9 8h6l-1 8H10l-1-8z\"/\u003e\u003ccircle cx=\"9\" cy=\"6\" r=\"1\"/\u003e\u003ccircle cx=\"15\" cy=\"6\" r=\"1\"/\u003e\u003cpath d=\"M12 16v2\"/\u003e\u003c/svg\u003e"}}},{"name":"Dark Fables","abilities":{"Dark Comedy":{"type":"Damage","cast_speed":"0.6s","base_value":"917 Shadow Damage (+50% conditional)","resource_delta":"None","range":"70m","summary":"Deals Shadow damage; +50% vs Stunned, Rooted, or Feared targets.","generative_icon":"\u003csvg class=\"w-6 h-6\" fill=\"none\" stroke=\"currentColor\" viewBox=\"0 0 24 24\" aria-hidden=\"true\" stroke-width=\"1.75\" stroke-linecap=\"round\" stroke-linejoin=\"round\"\u003e\u003ccircle cx=\"9\" cy=\"10\" r=\"3\"/\u003e\u003cpath d=\"M15 10a3 3 0 110 6\"/\u003e\u003cpath d=\"M9 13h2\"/\u003e\u003c/svg\u003e"},"Dance Through Flames":{"type":"Group Buff","cast_speed":"3.0s","base_value":"+15 Elemental Resistance","resource_delta":"None","range":"90m Aura","summary":"Grants party flat Elemental Resistance bonus. (Spell)","generative_icon":"\u003csvg class=\"w-6 h-6\" fill=\"none\" stroke=\"currentColor\" viewBox=\"0 0 24 24\" aria-hidden=\"true\" stroke-width=\"1.75\" stroke-linecap=\"round\" stroke-linejoin=\"round\"\u003e\u003cpath d=\"M12 4v12\"/\u003e\u003cpath d=\"M9 8l3-2 3 2\"/\u003e\u003cpath d=\"M8 18c1-2 2-3 4-3s3 1 4 3\"/\u003e\u003c/svg\u003e"},"The Tragic Betrayal":{"type":"Damage / CC","cast_speed":"1.0s","base_value":"1337 Mind Damage + Stun","resource_delta":"None","range":"45m","summary":"Deals Mind damage and Stuns for 3/6s. 45.0s Cooldown. (Spell)","generative_icon":"\u003csvg class=\"w-6 h-6\" fill=\"none\" stroke=\"currentColor\" viewBox=\"0 0 24 24\" aria-hidden=\"true\" stroke-width=\"1.75\" stroke-linecap=\"round\" stroke-linejoin=\"round\"\u003e\u003cpath d=\"M14 4l3 3-8 8H5v-4l9-9z\"/\u003e\u003cpath d=\"M16 6l2 2\"/\u003e\u003cpath d=\"M18 18l-3-3\"/\u003e\u003c/svg\u003e"},"Tales of Woe":{"type":"Damage / DoT","cast_speed":"0.6s","base_value":"1032 Shadow Damage + 1200 over 12s","resource_delta":"-175 Focus","range":"70m","summary":"Deals impact Shadow damage plus a direct damage over time effect.","generative_icon":"\u003csvg class=\"w-6 h-6\" fill=\"none\" stroke=\"currentColor\" viewBox=\"0 0 24 24\" aria-hidden=\"true\" stroke-width=\"1.75\" stroke-linecap=\"round\" stroke-linejoin=\"round\"\u003e\u003cpath d=\"M6 4h10v14H6z\"/\u003e\u003cpath d=\"M8 8h6M8 12h4\"/\u003e\u003cpath d=\"M16 10l2 4\"/\u003e\u003c/svg\u003e"},"Like Flitting Shadows":{"type":"Group Buff","cast_speed":"3.0s","base_value":"Negate Ranged Hits","resource_delta":"None","range":"90m Aura","summary":"Every 6s negates the next Ranged hit for each party member. (Spell)","generative_icon":"\u003csvg class=\"w-6 h-6\" fill=\"none\" stroke=\"currentColor\" viewBox=\"0 0 24 24\" aria-hidden=\"true\" stroke-width=\"1.75\" stroke-linecap=\"round\" stroke-linejoin=\"round\"\u003e\u003cpath d=\"M4 14l3-6M10 16l2-8M16 13l3-5\"/\u003e\u003cpath d=\"M6 18h12\"/\u003e\u003c/svg\u003e"},"A Sudden Fright":{"type":"Damage / CC","cast_speed":"0.2s","base_value":"1225 Shadow Damage + Fear","resource_delta":"None","range":"25m","summary":"Deals fast Shadow damage and Fears for 2/5s. 30.0s Cooldown. (Spell)","generative_icon":"\u003csvg class=\"w-6 h-6\" fill=\"none\" stroke=\"currentColor\" viewBox=\"0 0 24 24\" aria-hidden=\"true\" stroke-width=\"1.75\" stroke-linecap=\"round\" stroke-linejoin=\"round\"\u003e\u003cpath d=\"M12 5v4\"/\u003e\u003cpath d=\"M12 15v4\"/\u003e\u003cpath d=\"M5 12h4\"/\u003e\u003cpath d=\"M15 12h4\"/\u003e\u003c/svg\u003e"},"And Our Hero Falls!":{"type":"Debuff / Amplify","cast_speed":"1.0s","base_value":"+60% Damage Taken under 50% HP","resource_delta":"None","range":"60m","summary":"Target takes vastly increased execute damage for 6s. 90.0s Cooldown. (Spell)","generative_icon":"\u003csvg class=\"w-6 h-6\" fill=\"none\" stroke=\"currentColor\" viewBox=\"0 0 24 24\" aria-hidden=\"true\" stroke-width=\"1.75\" stroke-linecap=\"round\" stroke-linejoin=\"round\"\u003e\u003cpath d=\"M8 6l4 4 4-4\"/\u003e\u003cpath d=\"M12 10v8\"/\u003e\u003cpath d=\"M9 18h6\"/\u003e\u003c/svg\u003e"},"Die a Lonely Death":{"type":"Damage / CC Execute","cast_speed":"2.0s","base_value":"Delayed Shadow Damage (+100% if isolated)","resource_delta":"None","range":"60m","summary":"Snares target by 70% and chunks them at the end of the duration. 120.0s Cooldown. (Spell)","generative_icon":"\u003csvg class=\"w-6 h-6\" fill=\"none\" stroke=\"currentColor\" viewBox=\"0 0 24 24\" aria-hidden=\"true\" stroke-width=\"1.75\" stroke-linecap=\"round\" stroke-linejoin=\"round\"\u003e\u003ccircle cx=\"12\" cy=\"12\" r=\"7\"/\u003e\u003cpath d=\"M12 9v6\"/\u003e\u003ccircle cx=\"12\" cy=\"8\" r=\"1\"/\u003e\u003c/svg\u003e"}}},{"name":"Mummery","abilities":{"A Glimpse of Madness":{"type":"Spell","cast_speed":"0.2s","base_value":"Panic","resource_delta":"-75 Focus","range":"45m","summary":"Inflicts Panic. 4.0s Cooldown.","generative_icon":"\u003csvg class=\"w-6 h-6\" fill=\"none\" stroke=\"currentColor\" viewBox=\"0 0 24 24\" aria-hidden=\"true\" stroke-width=\"1.75\" stroke-linecap=\"round\" stroke-linejoin=\"round\"\u003e\u003ccircle cx=\"12\" cy=\"12\" r=\"3\"/\u003e\u003cpath d=\"M12 5v2M12 17v2M5 12h2M17 12h2M7 7l1.5 1.5M15.5 15.5L17 17\"/\u003e\u003c/svg\u003e"},"Screaming Shot":{"type":"Damage","cast_speed":"0.6s","base_value":"1078 Base Damage","resource_delta":"None","range":"70m","summary":"Deals Mind damage.","generative_icon":"\u003csvg class=\"w-6 h-6\" fill=\"none\" stroke=\"currentColor\" viewBox=\"0 0 24 24\" aria-hidden=\"true\" stroke-width=\"1.75\" stroke-linecap=\"round\" stroke-linejoin=\"round\"\u003e\u003ccircle cx=\"8\" cy=\"10\" r=\"3\"/\u003e\u003cpath d=\"M11 10h8\"/\u003e\u003cpath d=\"M17 8l3 2-3 2\"/\u003e\u003c/svg\u003e"},"As the Willow in a Storm":{"type":"Spell","cast_speed":"3.0s","base_value":"+25% Block Value, +10% Parry Chance","resource_delta":"None","range":"Self","summary":"Increases your party\u0027s Block Value by 25% and grants +10% Parry Chance.","generative_icon":"\u003csvg class=\"w-6 h-6\" fill=\"none\" stroke=\"currentColor\" viewBox=\"0 0 24 24\" aria-hidden=\"true\" stroke-width=\"1.75\" stroke-linecap=\"round\" stroke-linejoin=\"round\"\u003e\u003cpath d=\"M12 20V8\"/\u003e\u003cpath d=\"M12 12c-4-2-6-4-6-6\"/\u003e\u003cpath d=\"M12 14c4-1 6-3 6-5\"/\u003e\u003c/svg\u003e"},"The Darkest Hour":{"type":"Spell","cast_speed":"2.0s","base_value":"1225 Base Damage","resource_delta":"None","range":"60m","summary":"Deals Shadow damage around the target. Enemies hit are Silenced and Disarmed for 4/8 seconds. 60.0s Cooldown.","generative_icon":"\u003csvg class=\"w-6 h-6\" fill=\"none\" stroke=\"currentColor\" viewBox=\"0 0 24 24\" aria-hidden=\"true\" stroke-width=\"1.75\" stroke-linecap=\"round\" stroke-linejoin=\"round\"\u003e\u003ccircle cx=\"12\" cy=\"12\" r=\"5\"/\u003e\u003cpath d=\"M12 7v10\"/\u003e\u003cpath d=\"M7 12h10\" opacity=\"0.4\"/\u003e\u003c/svg\u003e"},"Bean Sidhe\u0027s Wail":{"type":"Spell","cast_speed":"1.0s","base_value":"1114 Base Damage","resource_delta":"None","range":"25m Cone","summary":"Inflicts Fear and deals Mind damage to targets in a 25m cone. 75.0s Cooldown.","generative_icon":"\u003csvg class=\"w-6 h-6\" fill=\"none\" stroke=\"currentColor\" viewBox=\"0 0 24 24\" aria-hidden=\"true\" stroke-width=\"1.75\" stroke-linecap=\"round\" stroke-linejoin=\"round\"\u003e\u003cpath d=\"M6 14c2-4 4-6 6-6s4 2 6 6\"/\u003e\u003cpath d=\"M8 14c1 2 2 3 4 3s3-1 4-3\"/\u003e\u003cpath d=\"M10 10h4\"/\u003e\u003c/svg\u003e"},"Death by a Thousand Cuts":{"type":"Spell","cast_speed":"3.0s","base_value":"Up to max 24% Damage Taken Debuff","resource_delta":"None","range":"Self","summary":"Your party inflicts a stacking debuff for 5 seconds when dealing Direct damage. This debuff increases damage taken by 3% per stack, up to a max of 24%.","generative_icon":"\u003csvg class=\"w-6 h-6\" fill=\"none\" stroke=\"currentColor\" viewBox=\"0 0 24 24\" aria-hidden=\"true\" stroke-width=\"1.75\" stroke-linecap=\"round\" stroke-linejoin=\"round\"\u003e\u003cpath d=\"M6 6l12 12M8 8l8 8M10 6l8 4M6 10l4 8M14 14l4-4\"/\u003e\u003c/svg\u003e"},"Dark Allure":{"type":"Spell","cast_speed":"7.0s","base_value":"334 Base Damage per second","resource_delta":"None","range":"60m","summary":"Channels to Charm an enemy and deal Mind damage each second for up to 6 seconds. 60.0s Cooldown.","generative_icon":"\u003csvg class=\"w-6 h-6\" fill=\"none\" stroke=\"currentColor\" viewBox=\"0 0 24 24\" aria-hidden=\"true\" stroke-width=\"1.75\" stroke-linecap=\"round\" stroke-linejoin=\"round\"\u003e\u003ccircle cx=\"12\" cy=\"12\" r=\"7\"/\u003e\u003ccircle cx=\"12\" cy=\"12\" r=\"2\"/\u003e\u003cpath d=\"M12 5c1 2 1 4 0 7\"/\u003e\u003c/svg\u003e"},"A Cautionary Tale":{"type":"Damage / AoE DoT","cast_speed":"0.6s","base_value":"917 Base Damage + 2000 DoT","resource_delta":"-400 Focus","range":"60m (15m AoE Radius)","summary":"Deals Shadow damage and an additional 2000 Shadow damage over 10 seconds. For the duration the target\u0027s allies take 300 Shadow damage each second while within 15m of them. 20.0s Cooldown.","generative_icon":"\u003csvg class=\"w-6 h-6\" fill=\"none\" stroke=\"currentColor\" viewBox=\"0 0 24 24\" aria-hidden=\"true\" stroke-width=\"1.75\" stroke-linecap=\"round\" stroke-linejoin=\"round\"\u003e\u003cpath d=\"M8 6h8v10H8z\"/\u003e\u003cpath d=\"M10 10h4M10 14h2\"/\u003e\u003cpath d=\"M14 18l2 2M10 18l-2 2\"/\u003e\u003c/svg\u003e"}}}]},{"class":"Empath","trees":[{"name":"Class Abilities","abilities":{"Clear Mind":{"type":"Spell (Friend)","cast_speed":"1.0s","base_value":null,"resource_delta":"-100 Panic","range":"45m","summary":"Reduces target\u0027s Panic by 350.","generative_icon":"\u003csvg class=\"w-6 h-6\" fill=\"none\" stroke=\"currentColor\" viewBox=\"0 0 24 24\" aria-hidden=\"true\" stroke-width=\"1.75\" stroke-linecap=\"round\" stroke-linejoin=\"round\"\u003e\u003ccircle cx=\"12\" cy=\"10\" r=\"4\"/\u003e\u003cpath d=\"M8 16c1-2 2.5-3 4-3s3 1 4 3\"/\u003e\u003cpath d=\"M6 8l2 2M18 8l-2 2\"/\u003e\u003c/svg\u003e"},"What Must Be Done":{"type":"Utility","cast_speed":"0.2s","base_value":null,"resource_delta":"None","range":"Self","summary":"Breaks all CC, and grants CC immunity for 10 seconds. 120.0s Cooldown.","generative_icon":"\u003csvg class=\"w-6 h-6\" fill=\"none\" stroke=\"currentColor\" viewBox=\"0 0 24 24\" aria-hidden=\"true\" stroke-width=\"1.75\" stroke-linecap=\"round\" stroke-linejoin=\"round\"\u003e\u003cpath d=\"M8 12h8\"/\u003e\u003cpath d=\"M10 8l-2 4 2 4M14 8l2 4-2 4\"/\u003e\u003cpath d=\"M6 6l12 12\" opacity=\"0.5\"/\u003e\u003c/svg\u003e"}}},{"name":"Tend the Enemy","abilities":{"Comhlacht Mallacht":{"type":"Spell","cast_speed":"2.0s","base_value":"1500 Base Damage","resource_delta":"-100 Faith, +1 Judgment","range":"60m","summary":"Deals Spirit damage. If target is Linked, reduces healing received by 25% for 4 seconds.","generative_icon":"\u003csvg class=\"w-6 h-6\" fill=\"none\" stroke=\"currentColor\" viewBox=\"0 0 24 24\" aria-hidden=\"true\" stroke-width=\"1.75\" stroke-linecap=\"round\" stroke-linejoin=\"round\"\u003e\u003cpath d=\"M12 4l2 6h6l-5 4 2 6-5-4-5 4 2-6-5-4h6z\"/\u003e\u003cpath d=\"M18 18l2 2\"/\u003e\u003c/svg\u003e"},"Fuil Truaillithe":{"type":"Spell","cast_speed":"2.0s","base_value":"1219 Base Damage","resource_delta":"-75 Faith, +1 Judgment","range":"45m","summary":"Deals 4550 Shadow damage over 21 seconds.","generative_icon":"\u003csvg class=\"w-6 h-6\" fill=\"none\" stroke=\"currentColor\" viewBox=\"0 0 24 24\" aria-hidden=\"true\" stroke-width=\"1.75\" stroke-linecap=\"round\" stroke-linejoin=\"round\"\u003e\u003cpath d=\"M12 4c-2 3-4 5-4 8a4 4 0 108 0c0-3-2-5-4-8z\"/\u003e\u003cpath d=\"M10 16l-1 2M14 16l1 2\"/\u003e\u003c/svg\u003e"},"Nasc Namhaid":{"type":"Spell","cast_speed":"0.2s","base_value":null,"resource_delta":"-25 Faith","range":"25m","summary":"Links you to an enemy. Reduces their Strength and Attunement while linked. 3.0s Cooldown.","generative_icon":"\u003csvg class=\"w-6 h-6\" fill=\"none\" stroke=\"currentColor\" viewBox=\"0 0 24 24\" aria-hidden=\"true\" stroke-width=\"1.75\" stroke-linecap=\"round\" stroke-linejoin=\"round\"\u003e\u003ccircle cx=\"7\" cy=\"12\" r=\"2\"/\u003e\u003ccircle cx=\"17\" cy=\"12\" r=\"2\"/\u003e\u003cpath d=\"M9 12h6\"/\u003e\u003cpath d=\"M17 10l2-2\"/\u003e\u003c/svg\u003e"},"Reabadh":{"type":"Spell (Friend Link)","cast_speed":"13.0s","base_value":"750 Base Damage","resource_delta":"None","range":"45m","summary":"Channels for up to 12 seconds. Spends 150 Health and deals Shadow damage to your Enemy Link each second.","generative_icon":"\u003csvg class=\"w-6 h-6\" fill=\"none\" stroke=\"currentColor\" viewBox=\"0 0 24 24\" aria-hidden=\"true\" stroke-width=\"1.75\" stroke-linecap=\"round\" stroke-linejoin=\"round\"\u003e\u003cpath d=\"M18 8l-4 4 4 4\"/\u003e\u003cpath d=\"M14 12H6\"/\u003e\u003ccircle cx=\"6\" cy=\"12\" r=\"2\"/\u003e\u003c/svg\u003e"},"Anam Truaillithe":{"type":"Spell","cast_speed":"0.2s","base_value":"1219 Base Damage","resource_delta":"-175 Faith, +1 Judgment","range":"45m","summary":"Deals Spirit damage over 21 seconds. 1.0s Cooldown.","generative_icon":"\u003csvg class=\"w-6 h-6\" fill=\"none\" stroke=\"currentColor\" viewBox=\"0 0 24 24\" aria-hidden=\"true\" stroke-width=\"1.75\" stroke-linecap=\"round\" stroke-linejoin=\"round\"\u003e\u003cpath d=\"M12 5c-3 2-5 5-5 8s2 6 5 6 5-3 5-6-2-6-5-8z\"/\u003e\u003cpath d=\"M10 12h4\"/\u003e\u003c/svg\u003e"},"Pairilis":{"type":"Spell","cast_speed":"0.2s","base_value":"938 Base Damage","resource_delta":"None","range":"45m","summary":"Deals Shadow damage and Disarms the target for 3/6 seconds. +50 damage if target is Linked to you. 20.0s Cooldown.","generative_icon":"\u003csvg class=\"w-6 h-6\" fill=\"none\" stroke=\"currentColor\" viewBox=\"0 0 24 24\" aria-hidden=\"true\" stroke-width=\"1.75\" stroke-linecap=\"round\" stroke-linejoin=\"round\"\u003e\u003cpath d=\"M14 4l3 3-8 8H5v-4l9-9z\"/\u003e\u003cpath d=\"M18 16l-3-3\"/\u003e\u003c/svg\u003e"},"Atreoru":{"type":"Spell (Friend)","cast_speed":"1.0s","base_value":null,"resource_delta":"-2 Judgment, +500 Faith","range":"Friend Link","summary":"For 10 seconds, each time your friendly link is dealt damage, 20% of that damage is prevented, and you are healed for the amount prevented. 2.0s Cooldown.","generative_icon":"\u003csvg class=\"w-6 h-6\" fill=\"none\" stroke=\"currentColor\" viewBox=\"0 0 24 24\" aria-hidden=\"true\" stroke-width=\"1.75\" stroke-linecap=\"round\" stroke-linejoin=\"round\"\u003e\u003cpath d=\"M12 3l7 3v6c0 3-2 5-7 7-5-2-7-4-7-7V6l7-3z\"/\u003e\u003cpath d=\"M12 11v4M10 13h4\"/\u003e\u003c/svg\u003e"},"Nochtadh":{"type":"Spell","cast_speed":"3.0s","base_value":"1406 Base Damage","resource_delta":"-3 Judgment, +750 Faith","range":"60m","summary":"Deals Spirit damage plus additional damage equal to 40% of your missing Health. Heals you for 50% of the damage dealt. (759 Base Healing)","generative_icon":"\u003csvg class=\"w-6 h-6\" fill=\"none\" stroke=\"currentColor\" viewBox=\"0 0 24 24\" aria-hidden=\"true\" stroke-width=\"1.75\" stroke-linecap=\"round\" stroke-linejoin=\"round\"\u003e\u003cpath d=\"M12 5c-4 0-7 3-7 7s3 7 7 7 7-3 7-7-3-7-7-7z\"/\u003e\u003ccircle cx=\"12\" cy=\"12\" r=\"2\"/\u003e\u003cpath d=\"M5 5l14 14\"/\u003e\u003c/svg\u003e"}}},{"name":"Tend the Spirit","abilities":{"Athghin":{"type":"Spell","cast_speed":"2.0s","base_value":"1519 Base Healing","resource_delta":"-2 Judgment, +500 Faith","range":"Self","summary":"Heals you for 4500 Health over 6 seconds.","generative_icon":"\u003csvg class=\"w-6 h-6\" fill=\"none\" stroke=\"currentColor\" viewBox=\"0 0 24 24\" aria-hidden=\"true\" stroke-width=\"1.75\" stroke-linecap=\"round\" stroke-linejoin=\"round\"\u003e\u003cpath d=\"M12 6v12\"/\u003e\u003cpath d=\"M8 10l4-4 4 4\"/\u003e\u003cpath d=\"M8 14l4 4 4-4\"/\u003e\u003c/svg\u003e"},"Comhroinn Fola":{"type":"Spell","cast_speed":"2.0s","base_value":"3645 Base Healing","resource_delta":"-75 Faith, +1 Judgment","range":"45m","summary":"Spends 1000 Health and heals the target. +40% healing if the target is linked to you. (1000 Base Damage)","generative_icon":"\u003csvg class=\"w-6 h-6\" fill=\"none\" stroke=\"currentColor\" viewBox=\"0 0 24 24\" aria-hidden=\"true\" stroke-width=\"1.75\" stroke-linecap=\"round\" stroke-linejoin=\"round\"\u003e\u003ccircle cx=\"8\" cy=\"10\" r=\"2\"/\u003e\u003ccircle cx=\"16\" cy=\"10\" r=\"2\"/\u003e\u003cpath d=\"M10 10h4\"/\u003e\u003cpath d=\"M12 12v6\"/\u003e\u003cpath d=\"M10 18h4\"/\u003e\u003c/svg\u003e"},"Nasc Cara":{"type":"Spell (Friend)","cast_speed":"0.2s","base_value":null,"resource_delta":"-25 Faith","range":"25m","summary":"Links you to an ally. Grants them increased Physical and Magic Armor Rating while linked. 3.0s Cooldown.","generative_icon":"\u003csvg class=\"w-6 h-6\" fill=\"none\" stroke=\"currentColor\" viewBox=\"0 0 24 24\" aria-hidden=\"true\" stroke-width=\"1.75\" stroke-linecap=\"round\" stroke-linejoin=\"round\"\u003e\u003ccircle cx=\"8\" cy=\"12\" r=\"2\"/\u003e\u003ccircle cx=\"16\" cy=\"12\" r=\"2\"/\u003e\u003cpath d=\"M10 12c0-2 1-3 2-3s2 1 2 3\"/\u003e\u003c/svg\u003e"},"Tonnadoir":{"type":"Spell","cast_speed":"13.0s","base_value":"810 Base Healing","resource_delta":"None","range":"45m","summary":"Channels for up to 12 seconds. Spends 150 Health and Heals your Friendly Link each second. (150 Base Damage)","generative_icon":"\u003csvg class=\"w-6 h-6\" fill=\"none\" stroke=\"currentColor\" viewBox=\"0 0 24 24\" aria-hidden=\"true\" stroke-width=\"1.75\" stroke-linecap=\"round\" stroke-linejoin=\"round\"\u003e\u003ccircle cx=\"6\" cy=\"12\" r=\"2\"/\u003e\u003ccircle cx=\"18\" cy=\"12\" r=\"2\"/\u003e\u003cpath d=\"M8 12c2-2 3-3 4-3s2 1 4 3\"/\u003e\u003c/svg\u003e"},"Comhroinn Cinniuint":{"type":"Spell","cast_speed":"0.2s","base_value":null,"resource_delta":"-200 Faith, +1 Judgment","range":"45m","summary":"Heals your Friendly Link over time. 8.0s Cooldown.","generative_icon":"\u003csvg class=\"w-6 h-6\" fill=\"none\" stroke=\"currentColor\" viewBox=\"0 0 24 24\" aria-hidden=\"true\" stroke-width=\"1.75\" stroke-linecap=\"round\" stroke-linejoin=\"round\"\u003e\u003cpath d=\"M8 8c2 2 4 3 4 6s-2 4-4 6\"/\u003e\u003cpath d=\"M16 8c-2 2-4 3-4 6s2 4 4 6\"/\u003e\u003cpath d=\"M10 12h4\"/\u003e\u003c/svg\u003e"},"Atreisiú":{"type":"Spell (Friend)","cast_speed":"0.2s","base_value":null,"resource_delta":"-2 Judgment, +500 Faith","range":"Friend Link","summary":"Reduces damage taken by your Friendly Link by 10% for 12 seconds. Double effectiveness while Friendly Link is below 50% Health. 2.0s Cooldown.","generative_icon":"\u003csvg class=\"w-6 h-6\" fill=\"none\" stroke=\"currentColor\" viewBox=\"0 0 24 24\" aria-hidden=\"true\" stroke-width=\"1.75\" stroke-linecap=\"round\" stroke-linejoin=\"round\"\u003e\u003ccircle cx=\"8\" cy=\"12\" r=\"2\"/\u003e\u003ccircle cx=\"16\" cy=\"12\" r=\"2\"/\u003e\u003cpath d=\"M10 12h4\"/\u003e\u003cpath d=\"M8 9v6M16 9v6\"/\u003e\u003c/svg\u003e"},"Balla Eiliminte":{"type":"Spell (Friend)","cast_speed":"0.2s","base_value":null,"resource_delta":"None","range":"Friend Link","summary":"Grants you immunity to Fire and Lighting damage and your Friendly Link +30% Fire and Lightning Resistance for 6 seconds. 120.0s Cooldown.","generative_icon":"\u003csvg class=\"w-6 h-6\" fill=\"none\" stroke=\"currentColor\" viewBox=\"0 0 24 24\" aria-hidden=\"true\" stroke-width=\"1.75\" stroke-linecap=\"round\" stroke-linejoin=\"round\"\u003e\u003cpath d=\"M12 3l7 3v6c0 2-2 4-7 6-5-2-7-4-7-6V6l7-3z\"/\u003e\u003cpath d=\"M9 10l6 4M15 10l-6 4\"/\u003e\u003c/svg\u003e"},"Comhinannu":{"type":"Spell (Friend)","cast_speed":"0.2s","base_value":null,"resource_delta":"None","range":"Friend Link","summary":"Removes all Debuffs from your Friendly Link and Heals them for 40% of your missing Health. Heals you both for 2400 Health over 12 seconds. 90.0s Cooldown.","generative_icon":"\u003csvg class=\"w-6 h-6\" fill=\"none\" stroke=\"currentColor\" viewBox=\"0 0 24 24\" aria-hidden=\"true\" stroke-width=\"1.75\" stroke-linecap=\"round\" stroke-linejoin=\"round\"\u003e\u003ccircle cx=\"8\" cy=\"12\" r=\"2\"/\u003e\u003ccircle cx=\"16\" cy=\"12\" r=\"2\"/\u003e\u003cpath d=\"M10 12h4\"/\u003e\u003cpath d=\"M12 8l1 2M12 16l-1 2\"/\u003e\u003c/svg\u003e"}}},{"name":"Tend the Body","abilities":{"Athchoirigh":{"type":"Resurrection","cast_speed":"9.0s","base_value":null,"resource_delta":"-225 Faith","range":"25m","summary":"Resurrects target ally with 25% max Health and Res Sickness.","generative_icon":"\u003csvg class=\"w-6 h-6\" fill=\"none\" stroke=\"currentColor\" viewBox=\"0 0 24 24\" aria-hidden=\"true\" stroke-width=\"1.75\" stroke-linecap=\"round\" stroke-linejoin=\"round\"\u003e\u003cpath d=\"M6 15c0-2 2-3 5-3s5 1 5 3\"/\u003e\u003cpath d=\"M5 15h10v2c0 2-2 3-5 3s-5-1-5-3v-2z\"/\u003e\u003cpath d=\"M12 6v5\"/\u003e\u003cpath d=\"M10 8l2-2 2 2\"/\u003e\u003c/svg\u003e"},"Saol Deontas":{"type":"Spell","cast_speed":"1.0s","base_value":"2430 Base Healing","resource_delta":"-100 Faith, +1 Judgment","range":"60m","summary":"Heal an ally for 1900 Health.","generative_icon":"\u003csvg class=\"w-6 h-6\" fill=\"none\" stroke=\"currentColor\" viewBox=\"0 0 24 24\" aria-hidden=\"true\" stroke-width=\"1.75\" stroke-linecap=\"round\" stroke-linejoin=\"round\"\u003e\u003cpath d=\"M8 11c0-2 2-3 4-3s4 1 4 3\"/\u003e\u003cpath d=\"M12 8v6\"/\u003e\u003cpath d=\"M10 6h4\"/\u003e\u003c/svg\u003e"},"Leigheas":{"type":"Spell","cast_speed":"2.0s","base_value":null,"resource_delta":"-75 Faith, +1 Judgment","range":"45m","summary":"Removes 1 Debuff from target ally.","generative_icon":"\u003csvg class=\"w-6 h-6\" fill=\"none\" stroke=\"currentColor\" viewBox=\"0 0 24 24\" aria-hidden=\"true\" stroke-width=\"1.75\" stroke-linecap=\"round\" stroke-linejoin=\"round\"\u003e\u003cpath d=\"M12 20V10\"/\u003e\u003cpath d=\"M12 10c-3-2-5-4-5-6a5 5 0 0110 0c0 2-2 4-5 6z\"/\u003e\u003cpath d=\"M16 6l2-2\"/\u003e\u003c/svg\u003e"},"Uacht Danu":{"type":"Heal","cast_speed":"0.2s","base_value":"2936 Base Healing","resource_delta":"-1 Judgment, +250 Faith","range":"45m","summary":"Heals the target. 4.0s Cooldown.","generative_icon":"\u003csvg class=\"w-6 h-6\" fill=\"none\" stroke=\"currentColor\" viewBox=\"0 0 24 24\" aria-hidden=\"true\" stroke-width=\"1.75\" stroke-linecap=\"round\" stroke-linejoin=\"round\"\u003e\u003cpath d=\"M8 10h8l-1 8H9l-1-8z\"/\u003e\u003cpath d=\"M10 6h4\"/\u003e\u003cpath d=\"M12 14v2\"/\u003e\u003c/svg\u003e"},"Ciorcal na Beatha":{"type":"Heal","cast_speed":"2.0s","base_value":"1215 Base Healing","resource_delta":"-2 Judgment, +500 Faith","range":"90m","summary":"Heals party for 2400 over 12 seconds.","generative_icon":"\u003csvg class=\"w-6 h-6\" fill=\"none\" stroke=\"currentColor\" viewBox=\"0 0 24 24\" aria-hidden=\"true\" stroke-width=\"1.75\" stroke-linecap=\"round\" stroke-linejoin=\"round\"\u003e\u003ccircle cx=\"12\" cy=\"12\" r=\"7\"/\u003e\u003ccircle cx=\"12\" cy=\"6\" r=\"1\"/\u003e\u003ccircle cx=\"17\" cy=\"9\" r=\"1\"/\u003e\u003ccircle cx=\"17\" cy=\"15\" r=\"1\"/\u003e\u003ccircle cx=\"12\" cy=\"18\" r=\"1\"/\u003e\u003ccircle cx=\"7\" cy=\"15\" r=\"1\"/\u003e\u003ccircle cx=\"7\" cy=\"9\" r=\"1\"/\u003e\u003c/svg\u003e"},"Slainte":{"type":"Heal","cast_speed":"0.2s","base_value":"911 Base Healing","resource_delta":"-100 Faith, +1 Judgment","range":"45m","summary":"Heals an ally for 1800 Health over 12 seconds. +50% healing if the target is Linked to you. 1.0s Cooldown.","generative_icon":"\u003csvg class=\"w-6 h-6\" fill=\"none\" stroke=\"currentColor\" viewBox=\"0 0 24 24\" aria-hidden=\"true\" stroke-width=\"1.75\" stroke-linecap=\"round\" stroke-linejoin=\"round\"\u003e\u003cpath d=\"M7 14h10l-1 4H8l-1-4z\"/\u003e\u003cpath d=\"M9 10h6\"/\u003e\u003cpath d=\"M12 6v4\"/\u003e\u003c/svg\u003e"},"Airde Friotaiocht":{"type":"Buff","cast_speed":"2.0s","base_value":null,"resource_delta":"-250 Faith, +1 Judgment","range":"45m","summary":"Grants an ally +60 Physical and Magical Armor Rating for 10 seconds.","generative_icon":"\u003csvg class=\"w-6 h-6\" fill=\"none\" stroke=\"currentColor\" viewBox=\"0 0 24 24\" aria-hidden=\"true\" stroke-width=\"1.75\" stroke-linecap=\"round\" stroke-linejoin=\"round\"\u003e\u003cpath d=\"M12 4l6 3v5c0 2-2.5 4-6 5-3.5-1-6-3-6-5V7l6-3z\"/\u003e\u003cpath d=\"M9 9l6 4\"/\u003e\u003c/svg\u003e"},"Seastan Deiridh":{"type":"Buff","cast_speed":"0.2s","base_value":null,"resource_delta":"None","range":"Party","summary":"Reduces damage taken by party by 50% for 8 seconds. 120.0s Cooldown.","generative_icon":"\u003csvg class=\"w-6 h-6\" fill=\"none\" stroke=\"currentColor\" viewBox=\"0 0 24 24\" aria-hidden=\"true\" stroke-width=\"1.75\" stroke-linecap=\"round\" stroke-linejoin=\"round\"\u003e\u003cpath d=\"M12 4v16\"/\u003e\u003cpath d=\"M8 8h8M7 12h10M8 16h8\"/\u003e\u003c/svg\u003e"}}}]},{"class":"Fianna","trees":[{"name":"Class Abilities","abilities":{"Bash":{"type":"Damage / CC","cast_speed":"0.2s","base_value":null,"resource_delta":"None","range":"6m","summary":"Deals damage and stuns the target.","generative_icon":"\u003csvg class=\"w-6 h-6\" fill=\"none\" stroke=\"currentColor\" viewBox=\"0 0 24 24\" aria-hidden=\"true\" stroke-width=\"1.75\" stroke-linecap=\"round\" stroke-linejoin=\"round\"\u003e\u003cpath d=\"M12 3l7 3v6c0 3-2 5-7 7-5-2-7-4-7-7V6l7-3z\"/\u003e\u003cpath d=\"M16 14l3 3\"/\u003e\u003c/svg\u003e"},"Shield Wall":{"type":"Mitigation","cast_speed":"0.2s","base_value":null,"resource_delta":"None","range":"Self","summary":"Significantly increases block chance and damage reduction.","generative_icon":"\u003csvg class=\"w-6 h-6\" fill=\"none\" stroke=\"currentColor\" viewBox=\"0 0 24 24\" aria-hidden=\"true\" stroke-width=\"1.75\" stroke-linecap=\"round\" stroke-linejoin=\"round\"\u003e\u003cpath d=\"M6 8l3 2v8l3 2 3-2v-8l3-2\"/\u003e\u003cpath d=\"M9 10h6M9 14h6\"/\u003e\u003c/svg\u003e"}}},{"name":"Prowess","abilities":{"Restore Vitae":{"type":"Heal Over Time","cast_speed":"0.2s","base_value":"1800 Healing over 18s","resource_delta":"+100 Courage","range":"Self","summary":"Heals you over time. 30.0s Cooldown. (Spell)","generative_icon":"\u003csvg class=\"w-6 h-6\" fill=\"none\" stroke=\"currentColor\" viewBox=\"0 0 24 24\" aria-hidden=\"true\" stroke-width=\"1.75\" stroke-linecap=\"round\" stroke-linejoin=\"round\"\u003e\u003cpath d=\"M12 20V10\"/\u003e\u003cpath d=\"M12 10c-3-2-5-4-5-6a5 5 0 0110 0c0 2-2 4-5 6z\"/\u003e\u003cpath d=\"M8 18h8\"/\u003e\u003c/svg\u003e"},"Rending Strike":{"type":"Damage / DoT","cast_speed":"0.6s","base_value":"479 Base Damage + 280 Slashing DoT","resource_delta":"+50 Courage","range":"6m","summary":"Deals Weapon damage and additional Slashing damage over 4s.","generative_icon":"\u003csvg class=\"w-6 h-6\" fill=\"none\" stroke=\"currentColor\" viewBox=\"0 0 24 24\" aria-hidden=\"true\" stroke-width=\"1.75\" stroke-linecap=\"round\" stroke-linejoin=\"round\"\u003e\u003cpath d=\"M14 4l4 4-9 9H5v-4l9-9z\"/\u003e\u003cpath d=\"M16 8l2-2\"/\u003e\u003cpath d=\"M8 16l-2 2\"/\u003e\u003c/svg\u003e"},"Unstoppable River":{"type":"Utility / Damage","cast_speed":"0.8s","base_value":"1037 Damage","resource_delta":"None","range":"45m","summary":"Removes all Control effects and charges the target; deals Weapon damage. 60.0s Cooldown.","generative_icon":"\u003csvg class=\"w-6 h-6\" fill=\"none\" stroke=\"currentColor\" viewBox=\"0 0 24 24\" aria-hidden=\"true\" stroke-width=\"1.75\" stroke-linecap=\"round\" stroke-linejoin=\"round\"\u003e\u003cpath d=\"M4 14c3-2 5-2 8 0s5 2 8 0\"/\u003e\u003cpath d=\"M6 18h12\"/\u003e\u003cpath d=\"M16 8l2-2M18 6l2 2\"/\u003e\u003c/svg\u003e"},"Rebuke Foe":{"type":"Damage / CC","cast_speed":"0.6s","base_value":"1596 Damage","resource_delta":"None","range":"6m","summary":"Deals Weapon damage and Knocks Back the target. 18.0s Cooldown.","generative_icon":"\u003csvg class=\"w-6 h-6\" fill=\"none\" stroke=\"currentColor\" viewBox=\"0 0 24 24\" aria-hidden=\"true\" stroke-width=\"1.75\" stroke-linecap=\"round\" stroke-linejoin=\"round\"\u003e\u003cpath d=\"M8 12h8\"/\u003e\u003cpath d=\"M6 12l3-3M18 12l-3-3\"/\u003e\u003cpath d=\"M12 8v8\"/\u003e\u003c/svg\u003e"},"Nature\u0027s Vengeance":{"type":"Damage (Execute)","cast_speed":"0.6s","base_value":"1436 Damage","resource_delta":"-125 Courage","range":"6m","summary":"Deals Weapon damage; increased equal to target\u0027s missing Health.","generative_icon":"\u003csvg class=\"w-6 h-6\" fill=\"none\" stroke=\"currentColor\" viewBox=\"0 0 24 24\" aria-hidden=\"true\" stroke-width=\"1.75\" stroke-linecap=\"round\" stroke-linejoin=\"round\"\u003e\u003cpath d=\"M6 20c4-6 8-10 12-12\"/\u003e\u003cpath d=\"M14 8l3 2\"/\u003e\u003cpath d=\"M10 12l-2 3\"/\u003e\u003c/svg\u003e"},"Whirlwind":{"type":"AoE Damage / CC","cast_speed":"0.2s","base_value":"1915 Damage","resource_delta":"-300 Courage","range":"Near enemies","summary":"Deals Weapon damage to nearby enemies; Knocks Back all except your target.","generative_icon":"\u003csvg class=\"w-6 h-6\" fill=\"none\" stroke=\"currentColor\" viewBox=\"0 0 24 24\" aria-hidden=\"true\" stroke-width=\"1.75\" stroke-linecap=\"round\" stroke-linejoin=\"round\"\u003e\u003cpath d=\"M12 6v12\"/\u003e\u003cpath d=\"M8 10l4-2 4 2\"/\u003e\u003cpath d=\"M8 14l4 2 4-2\"/\u003e\u003c/svg\u003e"},"Inescapable Vines":{"type":"CC / Utility","cast_speed":"0.2s","base_value":"Pull \u0026 Root","resource_delta":"None","range":"25m","summary":"Pulls the target to you, then Roots them for 3/5s. 45.0s Cooldown. (Spell)","generative_icon":"\u003csvg class=\"w-6 h-6\" fill=\"none\" stroke=\"currentColor\" viewBox=\"0 0 24 24\" aria-hidden=\"true\" stroke-width=\"1.75\" stroke-linecap=\"round\" stroke-linejoin=\"round\"\u003e\u003cpath d=\"M18 8l-6 6\"/\u003e\u003cpath d=\"M6 20c2-4 4-6 6-6\"/\u003e\u003ccircle cx=\"18\" cy=\"8\" r=\"2\"/\u003e\u003c/svg\u003e"},"Natural Strength":{"type":"AoE Damage / CC","cast_speed":"1.0s","base_value":"2394 Damage","resource_delta":"None","range":"6m","summary":"Deals Weapon damage in a cleave; Knocks Back and Stuns targets for 2/4s. 60.0s Cooldown.","generative_icon":"\u003csvg class=\"w-6 h-6\" fill=\"none\" stroke=\"currentColor\" viewBox=\"0 0 24 24\" aria-hidden=\"true\" stroke-width=\"1.75\" stroke-linecap=\"round\" stroke-linejoin=\"round\"\u003e\u003cpath d=\"M10 18V9l2-3 2 3v9\"/\u003e\u003cpath d=\"M8 12h8\"/\u003e\u003c/svg\u003e"}}},{"name":"Resilience","abilities":{"Forest Strike":{"type":"Damage / CC","cast_speed":"0.6s","base_value":"718 Damage","resource_delta":"+75 Courage","range":"6m","summary":"Deals Weapon damage and Snares.","generative_icon":"\u003csvg class=\"w-6 h-6\" fill=\"none\" stroke=\"currentColor\" viewBox=\"0 0 24 24\" aria-hidden=\"true\" stroke-width=\"1.75\" stroke-linecap=\"round\" stroke-linejoin=\"round\"\u003e\u003cpath d=\"M12 20V10\"/\u003e\u003cpath d=\"M12 10c-4-2-6-4-6-6\"/\u003e\u003cpath d=\"M14 4l3 3\"/\u003e\u003c/svg\u003e"},"Oakenshield":{"type":"Mitigation","cast_speed":"0.2s","base_value":"+2000 Block Value","resource_delta":"None","range":"Self","summary":"Increases Block Value of your next block within 5s by 2000. 12.0s Cooldown.","generative_icon":"\u003csvg class=\"w-6 h-6\" fill=\"none\" stroke=\"currentColor\" viewBox=\"0 0 24 24\" aria-hidden=\"true\" stroke-width=\"1.75\" stroke-linecap=\"round\" stroke-linejoin=\"round\"\u003e\u003cpath d=\"M12 3l7 3v6c0 3-2 5-7 7-5-2-7-4-7-7V6l7-3z\"/\u003e\u003cpath d=\"M12 8c-2 1-3 2-3 4\"/\u003e\u003c/svg\u003e"},"Nature\u0027s Defense":{"type":"Buff / Mitigation","cast_speed":"0.2s","base_value":"385 Earth Damage on parry","resource_delta":"None","range":"Self","summary":"Increases Parry Chance by 55% for 6s and deals Earth damage to attackers when you Parry. 60.0s Cooldown. (Spell)","generative_icon":"\u003csvg class=\"w-6 h-6\" fill=\"none\" stroke=\"currentColor\" viewBox=\"0 0 24 24\" aria-hidden=\"true\" stroke-width=\"1.75\" stroke-linecap=\"round\" stroke-linejoin=\"round\"\u003e\u003cpath d=\"M12 3l7 3v6c0 3-2 5-7 7-5-2-7-4-7-7V6l7-3z\"/\u003e\u003cpath d=\"M9 14l6-4\"/\u003e\u003c/svg\u003e"},"Strike of Wolves":{"type":"Damage / Buff","cast_speed":"0.6s","base_value":"1357 Damage","resource_delta":"-75 Courage","range":"6m","summary":"Deals Weapon damage. Usable again within 6s for increased Armor Rating.","generative_icon":"\u003csvg class=\"w-6 h-6\" fill=\"none\" stroke=\"currentColor\" viewBox=\"0 0 24 24\" aria-hidden=\"true\" stroke-width=\"1.75\" stroke-linecap=\"round\" stroke-linejoin=\"round\"\u003e\u003cpath d=\"M6 14c1-2 3-3 6-3s5 1 6 3\"/\u003e\u003cpath d=\"M8 14l-1 3M16 14l1 3\"/\u003e\u003ccircle cx=\"12\" cy=\"10\" r=\"2\"/\u003e\u003c/svg\u003e"},"Cry of the Forest":{"type":"Healing / Cleanse","cast_speed":"0.2s","base_value":"4746 Healing","resource_delta":"None","range":"Self","summary":"Heals you, removes and grants immunity to Root/Snare for 6s. 90.0s Cooldown. (Spell)","generative_icon":"\u003csvg class=\"w-6 h-6\" fill=\"none\" stroke=\"currentColor\" viewBox=\"0 0 24 24\" aria-hidden=\"true\" stroke-width=\"1.75\" stroke-linecap=\"round\" stroke-linejoin=\"round\"\u003e\u003cpath d=\"M10 8c0-2 1-3 2-3s2 1 2 3\"/\u003e\u003cpath d=\"M8 16c2-2 4-3 6-3s4 1 6 3\"/\u003e\u003cpath d=\"M12 4v2\"/\u003e\u003c/svg\u003e"},"Trust in the Forest":{"type":"Buff / Resource","cast_speed":"0.2s","base_value":"+10% Guts Threshold, +20% Guts Value","resource_delta":"+600 Courage (Scaled)","range":"Self","summary":"Grants Courage based on missing Health, and buffs defensive traits for 15s. 60.0s Cooldown. (Spell)","generative_icon":"\u003csvg class=\"w-6 h-6\" fill=\"none\" stroke=\"currentColor\" viewBox=\"0 0 24 24\" aria-hidden=\"true\" stroke-width=\"1.75\" stroke-linecap=\"round\" stroke-linejoin=\"round\"\u003e\u003cpath d=\"M12 20V8\"/\u003e\u003cpath d=\"M12 12c-4-2-6-4-6-6\"/\u003e\u003cpath d=\"M8 18h8\"/\u003e\u003c/svg\u003e"},"Nature\u0027s Cry":{"type":"Damage","cast_speed":"0.6s","base_value":"1915 Damage","resource_delta":"-100 Courage","range":"6m","summary":"Deals Weapon damage.","generative_icon":"\u003csvg class=\"w-6 h-6\" fill=\"none\" stroke=\"currentColor\" viewBox=\"0 0 24 24\" aria-hidden=\"true\" stroke-width=\"1.75\" stroke-linecap=\"round\" stroke-linejoin=\"round\"\u003e\u003cpath d=\"M10 8c0-2 1-3 2-3s2 1 2 3\"/\u003e\u003cpath d=\"M8 16c2-2 4-3 6-3s4 1 6 3\"/\u003e\u003cpath d=\"M6 10c2 0 3 1 4 2M18 10c-2 0-3 1-4 2\"/\u003e\u003c/svg\u003e"},"Roots of the Earth":{"type":"Utility / AoE CC","cast_speed":"0.8s","base_value":"1915 Damage","resource_delta":"None","range":"25m","summary":"Charges target, deals Weapon damage to nearby enemies, and Roots them for 4/8s. 90.0s Cooldown.","generative_icon":"\u003csvg class=\"w-6 h-6\" fill=\"none\" stroke=\"currentColor\" viewBox=\"0 0 24 24\" aria-hidden=\"true\" stroke-width=\"1.75\" stroke-linecap=\"round\" stroke-linejoin=\"round\"\u003e\u003cpath d=\"M6 18c2-4 4-6 6-6s4 2 6 6\"/\u003e\u003cpath d=\"M8 18h8\"/\u003e\u003cpath d=\"M10 14l2 4M14 14l-2 4\"/\u003e\u003c/svg\u003e"}}},{"name":"Form of Danu","abilities":{"Stony Reprisal":{"type":"Mitigation / Damage","cast_speed":"0.2s","base_value":"Reflects 50% damage","resource_delta":"None","range":"Self","summary":"Your next block within 5s reflects 50% damage as Earth Damage. 18.0s Cooldown.","generative_icon":"\u003csvg class=\"w-6 h-6\" fill=\"none\" stroke=\"currentColor\" viewBox=\"0 0 24 24\" aria-hidden=\"true\" stroke-width=\"1.75\" stroke-linecap=\"round\" stroke-linejoin=\"round\"\u003e\u003cpath d=\"M12 3l7 3v6c0 3-2 5-7 7-5-2-7-4-7-7V6l7-3z\"/\u003e\u003cpath d=\"M18 8l2-2M6 16l2 2\"/\u003e\u003c/svg\u003e"},"Earthen Strike":{"type":"Damage","cast_speed":"0.6s","base_value":"638 Earth Damage","resource_delta":"+75 Courage","range":"6m","summary":"Deals Earth damage.","generative_icon":"\u003csvg class=\"w-6 h-6\" fill=\"none\" stroke=\"currentColor\" viewBox=\"0 0 24 24\" aria-hidden=\"true\" stroke-width=\"1.75\" stroke-linecap=\"round\" stroke-linejoin=\"round\"\u003e\u003cpath d=\"M12 4v8\"/\u003e\u003cpath d=\"M8 18c1-2 2-3 4-3s3 1 4 3\"/\u003e\u003cpath d=\"M10 12h4\"/\u003e\u003c/svg\u003e"},"Forest of Thorns":{"type":"Buff / Mitigation","cast_speed":"0.2s","base_value":"Reflects 50% damage","resource_delta":"None","range":"Self","summary":"Increases Guts by 30% and reflects 50% damage for 10s. 60.0s Cooldown. (Spell)","generative_icon":"\u003csvg class=\"w-6 h-6\" fill=\"none\" stroke=\"currentColor\" viewBox=\"0 0 24 24\" aria-hidden=\"true\" stroke-width=\"1.75\" stroke-linecap=\"round\" stroke-linejoin=\"round\"\u003e\u003ccircle cx=\"12\" cy=\"12\" r=\"6\"/\u003e\u003cpath d=\"M12 6v2M12 16v2M6 12h2M16 12h2M8 8l1.5 1.5M15.5 15.5L17 17\"/\u003e\u003c/svg\u003e"},"Earth\u0027s Gift":{"type":"Buff / Mitigation","cast_speed":"0.2s","base_value":"+5% Physical, +10% Magic DR","resource_delta":"None","range":"Self","summary":"Grants Damage Reduction and reflects Ranged damage for 10s. 15.0s Cooldown. (Spell)","generative_icon":"\u003csvg class=\"w-6 h-6\" fill=\"none\" stroke=\"currentColor\" viewBox=\"0 0 24 24\" aria-hidden=\"true\" stroke-width=\"1.75\" stroke-linecap=\"round\" stroke-linejoin=\"round\"\u003e\u003cpath d=\"M8 10c0-2 2-3 4-3s4 1 4 3\"/\u003e\u003cpath d=\"M12 7v10\"/\u003e\u003cpath d=\"M9 18h6\"/\u003e\u003c/svg\u003e"},"Crushing Earth":{"type":"Damage","cast_speed":"0.6s","base_value":"1756 Earth Damage","resource_delta":"-125 Courage","range":"6m","summary":"Deals Earth damage; +25% Aftershock amount.","generative_icon":"\u003csvg class=\"w-6 h-6\" fill=\"none\" stroke=\"currentColor\" viewBox=\"0 0 24 24\" aria-hidden=\"true\" stroke-width=\"1.75\" stroke-linecap=\"round\" stroke-linejoin=\"round\"\u003e\u003cpath d=\"M12 4v8\"/\u003e\u003cpath d=\"M8 18h8\"/\u003e\u003cpath d=\"M6 18l2-2M18 18l-2-2\"/\u003e\u003c/svg\u003e"},"Nature\u0027s Sundering":{"type":"Damage","cast_speed":"0.2s","base_value":"Equal to Aftershock","resource_delta":"None","range":"45m","summary":"Fractures the target, dealing damage equal to their Aftershock and removing it. 60.0s Cooldown. (Spell)","generative_icon":"\u003csvg class=\"w-6 h-6\" fill=\"none\" stroke=\"currentColor\" viewBox=\"0 0 24 24\" aria-hidden=\"true\" stroke-width=\"1.75\" stroke-linecap=\"round\" stroke-linejoin=\"round\"\u003e\u003cpath d=\"M8 8l8 8\"/\u003e\u003cpath d=\"M12 6v12\"/\u003e\u003cpath d=\"M6 12h12\"/\u003e\u003c/svg\u003e"},"Cry of the Land":{"type":"Damage","cast_speed":"1.0s","base_value":"2554 Earth Damage","resource_delta":"-200 Courage (Refunded on Kill)","range":"6m","summary":"Deals Earth damage; refunds Courage cost if it kills the target.","generative_icon":"\u003csvg class=\"w-6 h-6\" fill=\"none\" stroke=\"currentColor\" viewBox=\"0 0 24 24\" aria-hidden=\"true\" stroke-width=\"1.75\" stroke-linecap=\"round\" stroke-linejoin=\"round\"\u003e\u003cpath d=\"M10 8c0-2 1-3 2-3s2 1 2 3\"/\u003e\u003cpath d=\"M6 14c2 0 4 1 6 3s4 3 6 3\"/\u003e\u003cpath d=\"M4 18h16\"/\u003e\u003c/svg\u003e"},"Living Stone":{"type":"Damage / Buff","cast_speed":"0.2s","base_value":"1915 Earth Damage","resource_delta":"None","range":"Self Impact","summary":"Deals Earth damage; grants Health Shield (50% missing Health) and +20% Armor Rating for 12s. 90.0s Cooldown.","generative_icon":"\u003csvg class=\"w-6 h-6\" fill=\"none\" stroke=\"currentColor\" viewBox=\"0 0 24 24\" aria-hidden=\"true\" stroke-width=\"1.75\" stroke-linecap=\"round\" stroke-linejoin=\"round\"\u003e\u003crect x=\"8\" y=\"6\" width=\"8\" height=\"12\" rx=\"2\"/\u003e\u003cpath d=\"M10 10h4M10 14h4\"/\u003e\u003cpath d=\"M12 4v2\"/\u003e\u003c/svg\u003e"}}}]},{"class":"Forest Stalker","trees":[{"name":"Class Abilities","abilities":{"Mark Target":{"type":"Spell","cast_speed":"0.2s","base_value":null,"resource_delta":"None","range":"70m","summary":"Increases the target\u0027s damage taken and prevents Stealth or entering the Veil for 10 seconds. 45.0s Cooldown.","generative_icon":"\u003csvg class=\"w-6 h-6\" fill=\"none\" stroke=\"currentColor\" viewBox=\"0 0 24 24\" aria-hidden=\"true\" stroke-width=\"1.75\" stroke-linecap=\"round\" stroke-linejoin=\"round\"\u003e\u003ccircle cx=\"12\" cy=\"12\" r=\"7\"/\u003e\u003ccircle cx=\"12\" cy=\"12\" r=\"2\"/\u003e\u003cpath d=\"M12 5v2M12 17v2M5 12h2M17 12h2\"/\u003e\u003c/svg\u003e"},"Reposition":{"type":"Ability","cast_speed":"0.2s","base_value":null,"resource_delta":"None","range":"Self","summary":"Increases your party\u0027s Movement Speed for 4 seconds. 60.0s Cooldown.","generative_icon":"\u003csvg class=\"w-6 h-6\" fill=\"none\" stroke=\"currentColor\" viewBox=\"0 0 24 24\" aria-hidden=\"true\" stroke-width=\"1.75\" stroke-linecap=\"round\" stroke-linejoin=\"round\"\u003e\u003cpath d=\"M5 12h10\"/\u003e\u003cpath d=\"M13 8l4 4-4 4\"/\u003e\u003cpath d=\"M8 8l-2 2M8 16l-2-2\"/\u003e\u003c/svg\u003e"}}},{"name":"Predation","abilities":{"Pick Off From Herd":{"type":"Damage","cast_speed":"0.6s","base_value":"1016 Base Damage","resource_delta":"175 Focus","range":"70m","summary":"Deals Weapon damage. +100% damage if the target isn\u0027t near any of their allies.","generative_icon":"\u003csvg class=\"w-6 h-6\" fill=\"none\" stroke=\"currentColor\" viewBox=\"0 0 24 24\" aria-hidden=\"true\" stroke-width=\"1.75\" stroke-linecap=\"round\" stroke-linejoin=\"round\"\u003e\u003ccircle cx=\"16\" cy=\"12\" r=\"2\"/\u003e\u003ccircle cx=\"7\" cy=\"9\" r=\"1\"/\u003e\u003ccircle cx=\"9\" cy=\"14\" r=\"1\"/\u003e\u003cpath d=\"M14 12H9\"/\u003e\u003c/svg\u003e"},"Arrow Shot":{"type":"Damage","cast_speed":"0.6s","base_value":"1423 Base Damage","resource_delta":"None","range":"70m","summary":"Deals Weapon damage.","generative_icon":"\u003csvg class=\"w-6 h-6\" fill=\"none\" stroke=\"currentColor\" viewBox=\"0 0 24 24\" aria-hidden=\"true\" stroke-width=\"1.75\" stroke-linecap=\"round\" stroke-linejoin=\"round\"\u003e\u003cpath d=\"M5 12h12\"/\u003e\u003cpath d=\"M15 9l4 3-4 3\"/\u003e\u003cpath d=\"M9 12l-2-2\"/\u003e\u003c/svg\u003e"},"Stealth":{"type":"Spell","cast_speed":"0.2s","base_value":null,"resource_delta":"None","range":"Self","summary":"You gain Stealth, making you invisible to enemies while outside their Detection Range. Becomes \"De-Stealth\" upon use. 12.0s Cooldown.","generative_icon":"\u003csvg class=\"w-6 h-6\" fill=\"none\" stroke=\"currentColor\" viewBox=\"0 0 24 24\" aria-hidden=\"true\" stroke-width=\"1.75\" stroke-linecap=\"round\" stroke-linejoin=\"round\"\u003e\u003cpath d=\"M8 10c0-2 1-3 2-3h4c1 0 2 1 2 3v4c0 2-1 3-2 3h-4c-1 0-2-1-2-3v-4z\"/\u003e\u003cpath d=\"M6 18h12\" opacity=\"0.4\"/\u003e\u003c/svg\u003e"},"Prey Sight":{"type":"Spell","cast_speed":"0.2s","base_value":null,"resource_delta":"None","range":"Self","summary":"Increases Stealth Detection Range by 25m and Critical Strike Chance by 8%.","generative_icon":"\u003csvg class=\"w-6 h-6\" fill=\"none\" stroke=\"currentColor\" viewBox=\"0 0 24 24\" aria-hidden=\"true\" stroke-width=\"1.75\" stroke-linecap=\"round\" stroke-linejoin=\"round\"\u003e\u003cpath d=\"M12 5c-4 0-7 3-7 7s3 7 7 7 7-3 7-7-3-7-7-7z\"/\u003e\u003ccircle cx=\"12\" cy=\"12\" r=\"2\"/\u003e\u003cpath d=\"M12 2v2\"/\u003e\u003c/svg\u003e"},"Scent Blood":{"type":"Damage / DoT","cast_speed":"0.6s","base_value":"762 Base Damage","resource_delta":"None","range":"70m","summary":"Deals Weapon damage an additional 6000 Slashing damage over 60s. The target leaves behind a visible blood trail for the duration of the DoT. 90.0s Cooldown.","generative_icon":"\u003csvg class=\"w-6 h-6\" fill=\"none\" stroke=\"currentColor\" viewBox=\"0 0 24 24\" aria-hidden=\"true\" stroke-width=\"1.75\" stroke-linecap=\"round\" stroke-linejoin=\"round\"\u003e\u003cpath d=\"M12 4c-1.5 2-3 4-3 6a3 3 0 106 0c0-2-1.5-4-3-6z\"/\u003e\u003cpath d=\"M8 18c2-1 4-1 6 0\"/\u003e\u003c/svg\u003e"},"Vital Focus":{"type":"Buff","cast_speed":"0.2s","base_value":null,"resource_delta":"150 Focus","range":"Self","summary":"Grants your next Weaponskill 100% Critically Hit Chance. 2.0s Cooldown.","generative_icon":"\u003csvg class=\"w-6 h-6\" fill=\"none\" stroke=\"currentColor\" viewBox=\"0 0 24 24\" aria-hidden=\"true\" stroke-width=\"1.75\" stroke-linecap=\"round\" stroke-linejoin=\"round\"\u003e\u003ccircle cx=\"12\" cy=\"12\" r=\"7\"/\u003e\u003cpath d=\"M12 8v4l2 2\"/\u003e\u003ccircle cx=\"12\" cy=\"12\" r=\"1\"/\u003e\u003c/svg\u003e"},"Crippling Shot":{"type":"Damage / CC","cast_speed":"0.6s","base_value":"1143 Base Damage","resource_delta":"None","range":"60m","summary":"Deals Weapon damage and Roots the target for 4/8 seconds. 45.0s Cooldown.","generative_icon":"\u003csvg class=\"w-6 h-6\" fill=\"none\" stroke=\"currentColor\" viewBox=\"0 0 24 24\" aria-hidden=\"true\" stroke-width=\"1.75\" stroke-linecap=\"round\" stroke-linejoin=\"round\"\u003e\u003cpath d=\"M5 12h10\"/\u003e\u003cpath d=\"M13 9l4 3-4 3\"/\u003e\u003cpath d=\"M10 18v-4\"/\u003e\u003c/svg\u003e"},"Parting Shot":{"type":"Damage / CC / Mobility","cast_speed":"0.2s","base_value":"1271 Base Damage","resource_delta":"None","range":"25m","summary":"Leaps backward and deals Weapon damage. Snares the target for 4/7 seconds. 45.0s Cooldown.","generative_icon":"\u003csvg class=\"w-6 h-6\" fill=\"none\" stroke=\"currentColor\" viewBox=\"0 0 24 24\" aria-hidden=\"true\" stroke-width=\"1.75\" stroke-linecap=\"round\" stroke-linejoin=\"round\"\u003e\u003cpath d=\"M5 14h10\"/\u003e\u003cpath d=\"M13 11l4 3-4 3\"/\u003e\u003cpath d=\"M16 6l2 2-2 2\"/\u003e\u003c/svg\u003e"},"Strike and Fade":{"type":"Damage / Utility","cast_speed":"2.0s","base_value":"1779 Base Damage","resource_delta":"300 Focus","range":"70m","summary":"Deals Weapon damage plus additional Weapon damage equal to 15% of target\u0027s missing Health. On a killing blow, you immediately gain Stealth and increased Movement Speed for 10 seconds.","generative_icon":"\u003csvg class=\"w-6 h-6\" fill=\"none\" stroke=\"currentColor\" viewBox=\"0 0 24 24\" aria-hidden=\"true\" stroke-width=\"1.75\" stroke-linecap=\"round\" stroke-linejoin=\"round\"\u003e\u003cpath d=\"M5 12h8\"/\u003e\u003cpath d=\"M11 9l4 3-4 3\"/\u003e\u003cpath d=\"M16 16l2-4-2-2\"/\u003e\u003c/svg\u003e"}}},{"name":"Thorn and Fang","abilities":{"Needle Shot":{"type":"Damage","cast_speed":"0.6s","base_value":"1194 Base Damage","resource_delta":"None","range":"70m","summary":"Deals Poison damage.","generative_icon":"\u003csvg class=\"w-6 h-6\" fill=\"none\" stroke=\"currentColor\" viewBox=\"0 0 24 24\" aria-hidden=\"true\" stroke-width=\"1.75\" stroke-linecap=\"round\" stroke-linejoin=\"round\"\u003e\u003cpath d=\"M6 12h11\"/\u003e\u003cpath d=\"M15 11l3 1-3 1\"/\u003e\u003cpath d=\"M9 12v-3\"/\u003e\u003c/svg\u003e"},"Poison Arrow":{"type":"Damage","cast_speed":"0.6s","base_value":"686 Base Damage","resource_delta":"100 Focus","range":"70m","summary":"Deals Poison damage and an additional 750 Poison damage over 9 seconds.","generative_icon":"\u003csvg class=\"w-6 h-6\" fill=\"none\" stroke=\"currentColor\" viewBox=\"0 0 24 24\" aria-hidden=\"true\" stroke-width=\"1.75\" stroke-linecap=\"round\" stroke-linejoin=\"round\"\u003e\u003cpath d=\"M5 12h11\"/\u003e\u003cpath d=\"M14 9l4 3-4 3\"/\u003e\u003cpath d=\"M12 6v3\"/\u003e\u003c/svg\u003e"},"Distilled Poison":{"type":"Spell","cast_speed":"0.2s","base_value":null,"resource_delta":"None","range":"Self","summary":"Increases Periodic Poison damage by 15%.","generative_icon":"\u003csvg class=\"w-6 h-6\" fill=\"none\" stroke=\"currentColor\" viewBox=\"0 0 24 24\" aria-hidden=\"true\" stroke-width=\"1.75\" stroke-linecap=\"round\" stroke-linejoin=\"round\"\u003e\u003cpath d=\"M9 6h6l-1 12h-4L9 6z\"/\u003e\u003cpath d=\"M10 4h4\"/\u003e\u003ccircle cx=\"12\" cy=\"14\" r=\"1\"/\u003e\u003c/svg\u003e"},"Spore Cloud":{"type":"AoE","cast_speed":"0.6s","base_value":null,"resource_delta":"250 Focus","range":"70m","summary":"Creates a cloud on impact that applies 1 Poison DoT stack every 2 seconds. Each stack deals 500 Poison damage over 5 seconds. Max 5 stacks. 12.0s Cooldown.","generative_icon":"\u003csvg class=\"w-6 h-6\" fill=\"none\" stroke=\"currentColor\" viewBox=\"0 0 24 24\" aria-hidden=\"true\" stroke-width=\"1.75\" stroke-linecap=\"round\" stroke-linejoin=\"round\"\u003e\u003cpath d=\"M8 14c1-2 2-3 4-3s3 1 4 3\"/\u003e\u003cpath d=\"M6 12c2 0 3-1 5-1s3 1 5 1\"/\u003e\u003ccircle cx=\"10\" cy=\"9\" r=\"1\"/\u003e\u003ccircle cx=\"15\" cy=\"10\" r=\"1\"/\u003e\u003c/svg\u003e"},"Fall Back":{"type":"Spell","cast_speed":"0.2s","base_value":null,"resource_delta":"None","range":"Self","summary":"Grants Movement Speed and Disarms you for 8 seconds. 30.0s Cooldown.","generative_icon":"\u003csvg class=\"w-6 h-6\" fill=\"none\" stroke=\"currentColor\" viewBox=\"0 0 24 24\" aria-hidden=\"true\" stroke-width=\"1.75\" stroke-linecap=\"round\" stroke-linejoin=\"round\"\u003e\u003cpath d=\"M19 12H9\"/\u003e\u003cpath d=\"M11 9l-4 3 4 3\"/\u003e\u003cpath d=\"M16 8l2 2-2 2\"/\u003e\u003c/svg\u003e"},"Opening Shot":{"type":"Damage","cast_speed":"0.6s","base_value":"1016 Base Damage","resource_delta":"150 Focus","range":"70m","summary":"Deals Weapon damage plus additional damage equal to 8% of target\u0027s current Health.","generative_icon":"\u003csvg class=\"w-6 h-6\" fill=\"none\" stroke=\"currentColor\" viewBox=\"0 0 24 24\" aria-hidden=\"true\" stroke-width=\"1.75\" stroke-linecap=\"round\" stroke-linejoin=\"round\"\u003e\u003cpath d=\"M5 12h12\"/\u003e\u003cpath d=\"M15 9l4 3-4 3\"/\u003e\u003cpath d=\"M12 4v3\"/\u003e\u003c/svg\u003e"},"Necrotic Toxin":{"type":"Damage","cast_speed":"0.6s","base_value":"2033 Base Damage","resource_delta":"300 Focus","range":"70m","summary":"Deals Weapon damage. Deals additional Poison damage over time and reduces the target\u0027s healing received by 50% for 12 seconds.","generative_icon":"\u003csvg class=\"w-6 h-6\" fill=\"none\" stroke=\"currentColor\" viewBox=\"0 0 24 24\" aria-hidden=\"true\" stroke-width=\"1.75\" stroke-linecap=\"round\" stroke-linejoin=\"round\"\u003e\u003ccircle cx=\"12\" cy=\"10\" r=\"3\"/\u003e\u003cpath d=\"M9 14h6\"/\u003e\u003cpath d=\"M10 18h4\"/\u003e\u003cpath d=\"M11 16h2\"/\u003e\u003c/svg\u003e"},"Death\u0027s Door":{"type":"Damage","cast_speed":"0.6s","base_value":"1779 Base Damage","resource_delta":"350 Focus","range":"70m","summary":"Deals Poison damage and increases Periodic Poison damage taken while below 30% Health by 200% for 20 seconds.","generative_icon":"\u003csvg class=\"w-6 h-6\" fill=\"none\" stroke=\"currentColor\" viewBox=\"0 0 24 24\" aria-hidden=\"true\" stroke-width=\"1.75\" stroke-linecap=\"round\" stroke-linejoin=\"round\"\u003e\u003cpath d=\"M8 6h8v12H8z\"/\u003e\u003cpath d=\"M12 10v4\"/\u003e\u003ccircle cx=\"12\" cy=\"16\" r=\"1\"/\u003e\u003c/svg\u003e"}}},{"name":"Stone Rain","abilities":{"Cloaked in Earth":{"type":"Spell","cast_speed":"0.2s","base_value":null,"resource_delta":"None","range":"Self","summary":"Reduces the damage of the next 3 hits received by 50%. 60.0s Cooldown.","generative_icon":"\u003csvg class=\"w-6 h-6\" fill=\"none\" stroke=\"currentColor\" viewBox=\"0 0 24 24\" aria-hidden=\"true\" stroke-width=\"1.75\" stroke-linecap=\"round\" stroke-linejoin=\"round\"\u003e\u003cpath d=\"M8 10c0-2 2-3 4-3s4 1 4 3v6c0 2-2 3-4 3s-4-1-4-3v-6z\"/\u003e\u003cpath d=\"M6 18c2-1 4-1 6 0\"/\u003e\u003c/svg\u003e"},"Earthen Arrow":{"type":"Damage","cast_speed":"0.6s","base_value":"1271 Base Damage","resource_delta":"None","range":"70m","summary":"Deals Earth damage.","generative_icon":"\u003csvg class=\"w-6 h-6\" fill=\"none\" stroke=\"currentColor\" viewBox=\"0 0 24 24\" aria-hidden=\"true\" stroke-width=\"1.75\" stroke-linecap=\"round\" stroke-linejoin=\"round\"\u003e\u003cpath d=\"M5 12h11\"/\u003e\u003cpath d=\"M14 9l4 3-4 3\"/\u003e\u003cpath d=\"M10 15l2 3\"/\u003e\u003c/svg\u003e"},"Pounding Shot":{"type":"Damage","cast_speed":"0.6s","base_value":"1321 Base Damage","resource_delta":"125 Focus","range":"70m","summary":"Deals Weapon damage plus additional Weapon damage equal to 40% of Aftershock on the target.","generative_icon":"\u003csvg class=\"w-6 h-6\" fill=\"none\" stroke=\"currentColor\" viewBox=\"0 0 24 24\" aria-hidden=\"true\" stroke-width=\"1.75\" stroke-linecap=\"round\" stroke-linejoin=\"round\"\u003e\u003cpath d=\"M5 12h10\"/\u003e\u003cpath d=\"M13 9l4 3-4 3\"/\u003e\u003cpath d=\"M8 18h8\"/\u003e\u003c/svg\u003e"},"Sniper\u0027s Shot":{"type":"Damage","cast_speed":"2.0s","base_value":"2033 Base Damage","resource_delta":"100 Focus","range":"70m","summary":"Deals Weapon damage. 100% Critical Hit Chance. 8.0s Cooldown.","generative_icon":"\u003csvg class=\"w-6 h-6\" fill=\"none\" stroke=\"currentColor\" viewBox=\"0 0 24 24\" aria-hidden=\"true\" stroke-width=\"1.75\" stroke-linecap=\"round\" stroke-linejoin=\"round\"\u003e\u003ccircle cx=\"12\" cy=\"12\" r=\"6\"/\u003e\u003ccircle cx=\"12\" cy=\"12\" r=\"2\"/\u003e\u003cpath d=\"M12 6v2M12 16v2M6 12h2M16 12h2\"/\u003e\u003cpath d=\"M5 12h3\"/\u003e\u003c/svg\u003e"},"Spike Field":{"type":"Spell","cast_speed":"1.0s","base_value":null,"resource_delta":"None","range":"Self","summary":"Creates an area of spike ground around you for 15 seconds that Snares enemies by 50% and deals 100 Earth damage per second while in the area. 45.0s Cooldown.","generative_icon":"\u003csvg class=\"w-6 h-6\" fill=\"none\" stroke=\"currentColor\" viewBox=\"0 0 24 24\" aria-hidden=\"true\" stroke-width=\"1.75\" stroke-linecap=\"round\" stroke-linejoin=\"round\"\u003e\u003cpath d=\"M8 16l2-6 2 6M12 16l2-6 2 6\"/\u003e\u003cellipse cx=\"12\" cy=\"18\" rx=\"8\" ry=\"2\"/\u003e\u003c/svg\u003e"},"Claws of Earth":{"type":"Damage / Debuff","cast_speed":"0.6s","base_value":"1271 Base Damage","resource_delta":"None","range":"70m","summary":"Deals Earth damage and debuffs the target for 12 seconds, causing Direct damage hits taken to deal added Earth damage. 45.0s Cooldown.","generative_icon":"\u003csvg class=\"w-6 h-6\" fill=\"none\" stroke=\"currentColor\" viewBox=\"0 0 24 24\" aria-hidden=\"true\" stroke-width=\"1.75\" stroke-linecap=\"round\" stroke-linejoin=\"round\"\u003e\u003cpath d=\"M8 16l-1-5M11 15l-1-6M14 16l-1-5\"/\u003e\u003cpath d=\"M6 18h12\"/\u003e\u003c/svg\u003e"},"Fist of Danu":{"type":"Damage","cast_speed":"0.6s","base_value":"1143 Base Damage","resource_delta":"None","range":"45m","summary":"Deals Earth damage and Knocks Back the target. 45.0s Cooldown.","generative_icon":"\u003csvg class=\"w-6 h-6\" fill=\"none\" stroke=\"currentColor\" viewBox=\"0 0 24 24\" aria-hidden=\"true\" stroke-width=\"1.75\" stroke-linecap=\"round\" stroke-linejoin=\"round\"\u003e\u003cpath d=\"M10 8c0-2 1-3 2-3s1 0 2 3v6c0 2-1 3-2 3s-2-1-2-3V8z\"/\u003e\u003cpath d=\"M18 12l-3-3\"/\u003e\u003c/svg\u003e"},"Spear of Lugh":{"type":"Damage","cast_speed":"0.6s","base_value":null,"resource_delta":"350 Focus","range":"90m","summary":"Fractures target, dealing increased damage.","generative_icon":"\u003csvg class=\"w-6 h-6\" fill=\"none\" stroke=\"currentColor\" viewBox=\"0 0 24 24\" aria-hidden=\"true\" stroke-width=\"1.75\" stroke-linecap=\"round\" stroke-linejoin=\"round\"\u003e\u003cpath d=\"M12 4l2 14\"/\u003e\u003cpath d=\"M10 6h4\"/\u003e\u003cpath d=\"M8 18l8-2\"/\u003e\u003c/svg\u003e"}}}]}]}]
